Workbook
Name CafeCOGS: Assumptions!B27
Name CafeGross: Assumptions!B26
Name CafeHrs: Assumptions!B32
Name CafeWage: Assumptions!B33
Name Cleaning: Assumptions!B39
Name CoachHrs: Assumptions!B30
Name CoachWage: Assumptions!B31
Name DaysOpenPerWeek: Assumptions!B9
Name FrontDeskHrs: Assumptions!B28
Name FrontDeskWage: Assumptions!B29
Name HoursOpenPerDay: Assumptions!B10
Name Insurance: Assumptions!B36
Name LeagueTeamFee: Assumptions!B22
Name LeagueTeams: Assumptions!B21
Name LessonRate: Assumptions!B20
Name LessonsPerWeek: Assumptions!B19
Name LoanAPR: Assumptions!B43
Name LoanPrincipal: Assumptions!B42
Name LoanTerm: Assumptions!B44
Name Marketing: Assumptions!B37
Name Members: Assumptions!B17
Name MembershipFee: Assumptions!B18
Name MiscOpex: Assumptions!B40
Name MonthlyCOGS: OPEX!$E$6
Name MonthlyDebtService: Financing!$I$3
Name MonthlyOpex: OPEX!$B$11
Name MonthlyPayroll: 'Staffing & Payroll'!$E$7
Name NumCourts: Assumptions!B8
Name OpeningCash: Assumptions!B41
Name PeakHoursShare: Assumptions!B11
Name RateOffPeak: Assumptions!B15
Name RatePeak: Assumptions!B14
Name Rent: Assumptions!B34
Name RetailCOGS: Assumptions!B25
Name RetailGross: Assumptions!B24
Name SeasonsPerYear: Assumptions!B23
Name Software: Assumptions!B38
Name TotalCapEx: 'CapEx & Sources'!E19
Name TotalRevenueRange: 'Revenue Model'!$I$5:$I$39
Name TurnTimeMin: Assumptions!B16
Name Utilities: Assumptions!B35
Name UtilOffPeak: Assumptions!B13
Name UtilPeak: Assumptions!B12

Sheet Assumptions
A1: Smashpoint Pickleball – Master Assumptions
A3: Category | B3: Value | C3: Notes
A4: Project Name | B4: Smashpoint Pickleball
A5: Location (City/State) | B5: Lorton, VA
A6: Start Date (MMM-YYYY) | B6: Jan-2026
A7: Number of Courts | B7: 8
A8: Days Open / Week | B8: 7
A9: Hours Open / Day | B9: 14
A10: Peak Hours Share (of day) | B10: 0.45
A11: Utilization – Peak | B11: 0.7
A12: Utilization – Off-Peak | B12: 0.4
A13: Court Rate – Peak ($/hr) | B13: 40
A14: Court Rate – Off-Peak ($/hr) | B14: 30
A15: Turn Time Between Bookings (min) | B15: 5
A16: Initial Members | B16: 50
A17: Membership Fee ($/mo) (ARPU) | B17: ='Memberships Revenue'!D52 -> 92.05
A18: Membership Growth Rate | B18: 0.05
A19: Lessons per Week | B19: 24 | C19: Ideally 24 per week
A20: Lesson Rate ($) | B20: 65
A21: League Teams per Season | B21: 12 | C21: Ideally 28 teams
A22: League Team Fee ($ per season) | B22: 250
A23: Seasons per Year | B23: 4
A24: Retail Gross ($/mo) | B24: 3000 | C24: Ideally want this to be around 4500 per month
A25: Retail COGS % | B25: 0.55
A26: Cafe Gross ($/mo) | B26: 5000 | C26: Ideally want this to be around 5000 per month
A27: Cafe COGS % | B27: 0.45
A28: Front Desk Hours / Week | B28: 196
A29: Front Desk Wage ($/hr) | B29: 18
A30: Coaches Hours / Week | B30: 40 | C30: Should be around 40 per week
A31: Coach Wage ($/hr) | B31: 30
A32: Cafe Hours / Week | B32: 60
A33: Cafe Wage ($/hr) | B33: 17
A34: Base Rent ($/mo) | B34: 40000 | C34: Originally 30K but taking conservative approach
A35: Utilities ($/mo) | B35: 6000 | C35: Originally 4.5K but taking conservative approach
A36: Insurance ($/mo) | B36: 4000 | C36: Estimated to be 2K but doubling value for conservative approach
A37: Marketing ($/mo) | B37: 4000 | C37: Estimated to be 4K but emphasizing substantial marketing campaign
A38: Software ($/mo) | B38: 2000 | C38: Estimated to be 0.8K but emphasizing strong software support
A39: Cleaning & Supplies ($/mo) | B39: 3000 | C39: Originally 1.5K but taking conservative approach
A40: Misc. Opex ($/mo) | B40: 2000 | C40: Estimated to be 1.2K but doubling value for conservative approach
A41: Opening Cash Balance ($) | B41: 100000
A42: Loan Principal ($) | B42: 2000000
A43: Loan APR (annual %) | B43: 0.095
A44: Loan Term (months) | B44: 120

Sheet CapEx & Sources
A1: Capital Expenditures and Sources/Uses
A3: Category | B3: Vendor/Notes | C3: Qty | D3: Unit Cost | E3: Line Total | G3: Sources & Uses
A4: Court surfacing & paint | C4: 8 | D4: 21000 | E4: =C4*D4 -> 168000 | G4: Item | H4: Amount
A5: Portable dividers/fencing | C5: 8 | D5: 4000 | E5: =C5*D5 -> 32000 | G5: Equity (plug) | H5: =H11-H6 -> -1100740
A6: Lighting (LED + install) | C6: 1 | D6: 100000 | E6: =C6*D6 -> 100000 | G6: SBA/Loan Proceeds | H6: =Assumptions!B42 -> 2000000
A7: Electronics (TVs,Tablets, etc.) | C7: 1 | D7: 20000 | E7: =C7*D7 -> 20000
A8: HVAC upgrades | C8: 1 | D8: 70000 | E8: =C8*D8 -> 70000 | G8: Total Sources | H8: =H6+H5 -> 899260
A9: Acoustic treatment | C9: 1 | D9: 70000 | E9: =C9*D9 -> 70000 | G9: Uses: CapEx Total | H9: =E22 -> 799260
A10: Nets & posts | C10: 8 | D10: 1200 | E10: =C10*D10 -> 9600 | G10: Opening Cash Reserve | H10: =Assumptions!B41 -> 100000
A11: Lockers/benches/seating | C11: 1 | D11: 20000 | E11: =C11*D11 -> 20000 | G11: Total Uses | H11: =H9+H10 -> 899260
A12: Pro shop fit-out | C12: 1 | D12: 45000 | E12: =C12*D12 -> 45000
A13: Cafe equipment & fit-out | C13: 1 | D13: 75000 | E13: =C13*D13 -> 75000
A14: Flooring (non-court) | C14: 1 | D14: 40000 | E14: =C14*D14 -> 40000 | G14: Debt Reserve (Surplus Cash) | H14: =ABS(H5) -> 1100740
A15: Permits/design/engineering | C15: 1 | D15: 50000 | E15: =C15*D15 -> 50000
A16: Security System | C16: 1 | D16: 15000 | E16: =C16*D16 -> 15000
A17: Access Control (Doors) | C17: 1 | D17: 12000 | E17: =C17*D17 -> 12000
D20: Subtotal: | E20: =SUM(E4:E19) -> 726600
D21: Contingency (10% of Subtotal): | E21: =E20*0.1 -> 72660
D22: Total CapEx: | E22: =E20+E21 -> 799260

Sheet Financing
A1: Loan Amortization (linked to Assumptions)
H2: Monthly Rate | I2: =Assumptions!B43/12 -> 0.0079166667
A3: Month # | B3: Beg Balance | C3: Payment | D3: Interest | E3: Principal | F3: End Balance | H3: Monthly Payment (PMT) | I3: =PMT(I2, Assumptions!B44, -Assumptions!B42) -> 25879.512
A4: 1 | B4: =Assumptions!B42 -> 2000000 | C4: =$I$3 -> 25879.512 | D4: =B4*$I$2 -> 15833.333 | E4: =C4-D4 -> 10046.178 | F4: =B4-E4 -> 1989953.8
A5: 2 | B5: =F4 -> 1989953.8 | C5: =$I$3 -> 25879.512 | D5: =B5*$I$2 -> 15753.801 | E5: =C5-D5 -> 10125.71 | F5: =B5-E5 -> 1979828.1
A6: 3 | B6: =F5 -> 1979828.1 | C6: =$I$3 -> 25879.512 | D6: =B6*$I$2 -> 15673.639 | E6: =C6-D6 -> 10205.872 | F6: =B6-E6 -> 1969622.2
A7: 4 | B7: =F6 -> 1969622.2 | C7: =$I$3 -> 25879.512 | D7: =B7*$I$2 -> 15592.843 | E7: =C7-D7 -> 10286.669 | F7: =B7-E7 -> 1959335.6
A8: 5 | B8: =F7 -> 1959335.6 | C8: =$I$3 -> 25879.512 | D8: =B8*$I$2 -> 15511.407 | E8: =C8-D8 -> 10368.105 | F8: =B8-E8 -> 1948967.5
A9: 6 | B9: =F8 -> 1948967.5 | C9: =$I$3 -> 25879.512 | D9: =B9*$I$2 -> 15429.326 | E9: =C9-D9 -> 10450.186 | F9: =B9-E9 -> 1938517.3
A10: 7 | B10: =F9 -> 1938517.3 | C10: =$I$3 -> 25879.512 | D10: =B10*$I$2 -> 15346.595 | E10: =C10-D10 -> 10532.916 | F10: =B10-E10 -> 1927984.4
A11: 8 | B11: =F10 -> 1927984.4 | C11: =$I$3 -> 25879.512 | D11: =B11*$I$2 -> 15263.21 | E11: =C11-D11 -> 10616.302 | F11: =B11-E11 -> 1917368.1
A12: 9 | B12: =F11 -> 1917368.1 | C12: =$I$3 -> 25879.512 | D12: =B12*$I$2 -> 15179.164 | E12: =C12-D12 -> 10700.348 | F12: =B12-E12 -> 1906667.7
A13: 10 | B13: =F12 -> 1906667.7 | C13: =$I$3 -> 25879.512 | D13: =B13*$I$2 -> 15094.453 | E13: =C13-D13 -> 10785.059 | F13: =B13-E13 -> 1895882.7
A14: 11 | B14: =F13 -> 1895882.7 | C14: =$I$3 -> 25879.512 | D14: =B14*$I$2 -> 15009.071 | E14: =C14-D14 -> 10870.44 | F14: =B14-E14 -> 1885012.2
A15: 12 | B15: =F14 -> 1885012.2 | C15: =$I$3 -> 25879.512 | D15: =B15*$I$2 -> 14923.013 | E15: =C15-D15 -> 10956.498 | F15: =B15-E15 -> 1874055.7
A16: 13 | B16: =F15 -> 1874055.7 | C16: =$I$3 -> 25879.512 | D16: =B16*$I$2 -> 14836.274 | E16: =C16-D16 -> 11043.237 | F16: =B16-E16 -> 1863012.5
... A123: 120 | B123: =F122 -> 25676.241 | C123: =$I$3 -> 25879.512 | D123: =B123*$I$2 -> 203.27024 | E123: =C123-D123 -> 25676.241 | F123: =B123-E123 -> -3.1286618e-10

Sheet Memberships Revenue
A1: Smashpoint Memberships – Tiers, Pricing, Revenue & KPIs
A4: Tier | B4: Monthly Price | C4: Annual Price (if offered) | D4: Initiation Fee | E4: Booking Window (days) | F4: Court Discount (%) | G4: Open Play (member price) | H4: Guest Passes / mo | I4: Lesson Discount (%) | J4: League Priority (Y/N) | K4: Cancellation Window (hrs) | L4: Freeze Months / yr | M4: Notes
A5: Non‑Member Day Pass | G5: 12 | J5: N | M5: Single‑day access (no advance booking)
A6: Weekday AM (Off‑Peak) | B6: 35 | D6: 0 | E6: 2 | F6: 0.3 | G6: 6 | H6: 0 | I6: 0.1 | J6: N | K6: 12 | L6: 1 | M6: Access M‑F before 12pm; limited booking
A7: Standard | B7: 60 | C7: 689 | D7: 0 | E7: 7 | F7: 0.25 | G7: 8 | H7: 1 | I7: 0.1 | J7: Y | K7: 12 | L7: 1 | M7: Best for 1–3x/week players
A8: Plus | B8: 100 | C8: 999 | D8: 0 | E8: 10 | F8: 0.35 | G8: 6 | H8: 2 | I8: 0.15 | J8: Y | K8: 6 | L8: 2 | M8: Longer booking, more discounts, extra guest passes
A9: Advanced | B9: 140 | C9: 1399 | D9: 0 | E9: 14 | F9: 0.4 | G9: 5 | H9: 4 | I9: 0.2 | J9: Y | K9: 24 | L9: 3 | M9: Highest Non-Founder Tier
A10: Family (3 people) | B10: 179 | C10: 1900 | D10: 0 | E10: 10 | F10: 0.3 | G10: 6 | H10: 2 | I10: 0.15 | J10: Y | K10: 12 | L10: 2 | M10: Addl. family +$25/mo each
A11: Corporate (per seat) | B11: 65 | D11: 0 | E11: 7 | F11: 0.25 | G11: 8 | H11: 0 | I11: 0.1 | J11: Y | K11: 12 | L11: 0 | M11: Requires 10+ seats; pooled billing
A12: Founders (limited) | B12: 119 | C12: 1299 | D12: 0 | E12: 21 | F12: 0.4 | G12: 4 | H12: 4 | I12: 0.2 | J12: Y | K12: 24 | L12: 3 | M12: Limited quantity; merch & early event access (first 100)
A15: Assumptions (Edit)
A16: Total Members | B16: =Assumptions!B16 -> 50
A17: % Monthly vs Annual purchasers (monthly) | B17: 1
A18: Day Pass Price (Non‑Member) | B18: 12
A19: Monthly Day Pass Count (avg) | B19: 220
A20: Churn (monthly, starting point) | B20: 0.04
A21: New Member Adds / Month | B21: 30
A23: Member Distribution by Tier (sums to 100%)
A24: Tier | B24: % of Members
A25: Weekday AM (Off‑Peak) | B25: 0.08
A26: Standard | B26: 0.44
A27: Plus | B27: 0.21
A28: Advanced | B28: 0.12
A29: Family (3 people) | B29: 0.12
A30: Corporate (per seat) | B30: 0
A31: Founders (limited) | B31: 0.03
A34: Calculated Members & Revenue
A35: Tier | B35: Members (calc) | C35: Monthly Price | D35: Annual Price | E35: % Monthly Buyers | F35: Monthly MRR | G35: Annual MRR (monthly equivalent)
A36: Weekday AM (Off‑Peak) | B36: =$B$16*$B$25 -> 4 | C36: =VLOOKUP(A36, $A$5:$M$12, 2, FALSE) -> 35 | D36: =VLOOKUP(A36, $A$5:$M$12, 3, FALSE) -> 0 | E36: =$B$17 -> 1 | F36: =B36*E36*C36 -> 140 | G36: =B36*(1-E36)*(D36/12) -> 0
A37: Standard | B37: =$B$16*$B$26 -> 22 | C37: =VLOOKUP(A37, $A$5:$M$12, 2, FALSE) -> 60 | D37: =VLOOKUP(A37, $A$5:$M$12, 3, FALSE) -> 689 | E37: =$B$17 -> 1 | F37: =B37*E37*C37 -> 1320 | G37: =B37*(1-E37)*(D37/12) -> 0
A38: Plus | B38: =$B$16*$B$27 -> 10.5 | C38: =VLOOKUP(A38, $A$5:$M$12, 2, FALSE) -> 100 | D38: =VLOOKUP(A38, $A$5:$M$12, 3, FALSE) -> 999 | E38: =$B$17 -> 1 | F38: =B38*E38*C38 -> 1050 | G38: =B38*(1-E38)*(D38/12) -> 0
A39: Advanced | B39: =$B$16*$B$28 -> 6 | C39: =VLOOKUP(A39, $A$5:$M$12, 2, FALSE) -> 140 | D39: =VLOOKUP(A39, $A$5:$M$12, 3, FALSE) -> 1399 | E39: =$B$17 -> 1 | F39: =B39*E39*C39 -> 840 | G39: =B39*(1-E39)*(D39/12) -> 0
A40: Family (3 people) | B40: =$B$16*$B$29 -> 6 | C40: =VLOOKUP(A40, $A$5:$M$12, 2, FALSE) -> 179 | D40: =VLOOKUP(A40, $A$5:$M$12, 3, FALSE) -> 1900 | E40: =$B$17 -> 1 | F40: =B40*E40*C40 -> 1074 | G40: =B40*(1-E40)*(D40/12) -> 0
A41: Corporate (per seat) | B41: =$B$16*$B$30 -> 0 | C41: =VLOOKUP(A41, $A$5:$M$12, 2, FALSE) -> 65 | D41: =VLOOKUP(A41, $A$5:$M$12, 3, FALSE) -> 0 | E41: =$B$17 -> 1 | F41: =B41*E41*C41 -> 0 | G41: =B41*(1-E41)*(D41/12) -> 0
A42: Founders (limited) | B42: =$B$16*$B$31 -> 1.5 | C42: =VLOOKUP(A42, $A$5:$M$12, 2, FALSE) -> 119 | D42: =VLOOKUP(A42, $A$5:$M$12, 3, FALSE) -> 1299 | E42: =$B$17 -> 1 | F42: =B42*E42*C42 -> 178.5 | G42: =B42*(1-E42)*(D42/12) -> 0
A43: TOTAL | B43: =SUM(B35:B42) -> 50 | F43: =SUM(F35:F42) -> 4602.5 | G43: =SUM(G35:G42) -> 0
A45: Non‑Member Day Pass Revenue
A46: Price | B46: Passes / Month | C46: Revenue / Month
A47: =$B$18 -> 12 | B47: =$B$19 -> 220 | C47: =A47*B47 -> 2640
A50: KPIs (auto)
A51: MRR (Members only) | B51: MRR (Annualized equivalents) | C51: Total MRR (Members + Day Pass) | D51: ARPU (Members only) | E51: Member Mix: %Plus | F51: Member Mix: %Standard | G51: Churned / Month (est.) | H51: Net Adds / Month (est.)
A52: =F43 -> 4602.5 | B52: =G43 -> 0 | C52: =A47+F43+G43 -> 4614.5 | D52: =(F43+G43)/B43 -> 92.05 | E52: =$B$27 -> 0.21 | F52: =$B$26 -> 0.44 | G52: =B43*$B$20 -> 2 | H52: =$B$21-G52 -> 28

Sheet Court Revenue (36m)
A1: Membership-Driven Court Revenue Model – 36 months (Monthly) – v4 (Seasonality)
A2: Seasonality Index scales demand for member & non-member reservations and open play.
A4: INPUTS – Facility & Schedule | E4: INPUTS – Utilization Baselines (Members) | H4: SEASONALITY – Monthly Index
A5: Courts (count) | B5: =Assumptions!B7 -> 8 | E5: Baseline utilization – Peak (weekday) – Members | F5: 0.75 | H5: M1 | I5: 2
A6: Days open per week | B6: =Assumptions!B8 -> 7 | E6: Baseline utilization – Off-peak (weekday) – Members | F6: 0.4 | H6: M2 | I6: 1.5
A7: Hours open per day | B7: 14 | E7: Baseline utilization – Peak (weekend) – Members | F7: 0.85 | H7: M3 | I7: 1.5
A8: Peak hours share of day | B8: =(B7-4)/B7 -> 0.71428571 | E8: Baseline utilization – Off-peak (weekend) – Members | F8: 0.5 | H8: M4 | I8: 1.2
A9: Weekend share of days | B9: 0.28571429 | H9: M5 | I9: 1
A10: Reservation share of total court time (vs open play) | B10: 0.25 | H10: M6 | I10: 0.8
A11: INPUTS – Pricing | E11: INPUTS – Policy & Behavior (Members) | H11: M7 | I11: 0.8
A12: Peak rate – Non-member ($/court-hr) | B12: =Assumptions!B13 -> 40 | E12: No-show rate (paid/no-refund portion) | F12: 0.05 | H12: M8 | I12: 0.8
A13: Off-peak rate – Non-member ($/court-hr) | B13: =Assumptions!B14 -> 30 | E13: Member booking share of reservations (target) | F13: 0.7 | H13: M9 | I13: 1
A14: Member discount on court rate | B14: 0.25 | E14: Booking window uplift (members vs non) | F14: 0.05 | H14: M10 | I14: 1.2
A15: Open Play price – Member ($/session) | B15: 5 | H15: M11 | I15: 1.5
A16: Open Play price – Non-member ($/session) | B16: 8 | H16: M12 | I16: 2
A17: Open Play session length (min) | B17: 60 | H17: Notes:
A19: INPUTS – Membership Growth (drives demand) | E19: INPUTS – Non-member Reservation Demand
A20: Starting Members (Month 1) | B20: =Assumptions!B16 -> 50 | E20: Baseline utilization – Peak (weekday) – Non-members | F20: 0.5
A21: Monthly Member Growth Rate (%) | B21: =Assumptions!B18 -> 0.05 | E21: Baseline utilization – Off-peak (weekday) – Non-members | F21: 0.4
A22: Max Member Capacity (optional) | B22: 1000 | E22: Baseline utilization – Peak (weekend) – Non-members | F22: 0.5
A23: % Members who reserve monthly | B23: 0.5 | E23: Baseline utilization – Off-peak (weekend) – Non-members | F23: 0.4
A24: Avg reservations per reserving member / month | B24: 2 | E24: Marketing uplift – Non-members (reservations) | F24: 0.1
A25: Avg reservation duration (min) | B25: 60 | E25: Non-member reservation cap (% of reservation capacity) | F25: 1
A26: Avg open-play sessions / member / month | B26: 12
A27: Open Play players per court capacity (per hour) | B27: 6
A29: HELPERS | E29: Blended Utilization
A30: Total Court Hours / month | B30: =B7*B5*4.33*B6 -> 3394.72 | E30: Blended Peak Utilization – Members | F30: =(1-B8)*F5 + B8*F7 -> 0.82142857
A31: Peak Hours / month | B31: =B30*B8 -> 2424.8 | E31: Blended Off-Peak Utilization – Members | F31: =(1-B8)*F6 + B8*F8 -> 0.47142857
A32: Off-Peak Hours / month | B32: =B30*(1-B8) -> 969.92
A33: Open Play Hours Share | B33: =(1-B10) -> 0.75 | E33: Blended Utilization – Non-members
E34: Blended Peak Utilization – Non-members | F34: =(1-B8)*F20 + B8*F22 -> 0.5
E35: Blended Off-Peak Utilization – Non-members | F35: =(1-B8)*F21 + B8*F23 -> 0.4
E37: Reservation Capacity (attended hours cap)
E38: Reservation Capacity Hours / month | F38: =(B31*F30 + B32*F31)*B10 -> 612.262
A39: Reservation Duration (hours) | B39: =B25/60 -> 1
A40: Open Play Session Length (hours) | B40: =B17/60 -> 1 | E40: Reservation Rates (blended)
E41: Blended Non-member Reservation Rate ($/hr) | F41: =(B12*B31 + B13*B32)/(B31+B32) -> 37.142857
E42: Blended Member Reservation Rate ($/hr) | F42: =F41*(1-B14) -> 27.857143
A44: Month | B44: Seasonality Index | C44: Members | D44: Member Reservation Hours (raw) | E44: Member Reservation Hours (capped) | F44: Non-member Reservation Demand Hours | G44: Non-member Reservation Hours (actual) | H44: Avg Reservation Rate ($/hr) | I44: Reservation Revenue (attended) | J44: No-show Revenue | K44: Member Open Play Hours (raw) | L44: Member Open Play Hours (capped) | M44: Member Open Play Sessions | N44: Member Open Play Revenue | O44: Non-member Open Play Hours | P44: Non-member Open Play Sessions | Q44: Non-member Open Play Revenue | R44: TOTAL Court Revenue ($/mo)
A45: M1 | B45: =INDEX($I$5:$I$16, 1+MOD(1-1,12)) -> 2 | C45: =MIN(B20,$B$22) -> 50 | D45: =C45*$B$23*$B$24*$B$39*B45 -> 100 | E45: =MIN(D45, $F$38) -> 100 | F45: =(($B$31*$F$34*$B$10) + ($B$32*$F$35*$B$10))*(1+$F$24)*B45 -> 880.2024 | G45: =MIN(F45, MAX($F$38-E45,0), $F$25*$F$38) -> 512.262 | H45: =IFERROR(($F$42*E45 + $F$41*G45)/(E45+G45),0) -> 35.626233 | I45: =(E45+G45)*H45 -> 21812.589 | J45: =H45*(E45+G45)*$F$12 -> 1090.6294 | K45: =C45*$B$26*$B$40*B45 -> 1200 | L45: =MIN(K45, $B$30*(1-$B$10)) -> 1200 | M45: =IFERROR(L45/$B$40,0) -> 1200 | N45: =M45*$B$15 -> 6000 | O45: =MAX($B$30*(1-$B$10)-L45,0) -> 1346.04 | P45: =IFERROR(O45/$B$40,0) -> 1346.04 | Q45: =P45*$B$16 -> 10768.32 | R45: =I45+J45+N45+Q45 -> 39671.538
A46: M2 | B46: =INDEX($I$5:$I$16, 1+MOD(2-1,12)) -> 1.5 | C46: =MIN(C45*(1+$B$21), $B$22) -> 52.5 | D46: =C46*$B$23*$B$24*$B$39*B46 -> 78.75 | E46: =MIN(D46, $F$38) -> 78.75 | F46: =(($B$31*$F$34*$B$10) + ($B$32*$F$35*$B$10))*(1+$F$24)*B46 -> 660.1518 | G46: =MIN(F46, MAX($F$38-E46,0), $F$25*$F$38) -> 533.512 | H46: =IFERROR(($F$42*E46 + $F$41*G46)/(E46+G46),0) -> 35.948516 | I46: =(E46+G46)*H46 -> 22009.91 | J46: =H46*(E46+G46)*$F$12 -> 1100.4955 | K46: =C46*$B$26*$B$40*B46 -> 945 | L46: =MIN(K46, $B$30*(1-$B$10)) -> 945 | M46: =IFERROR(L46/$B$40,0) -> 945 | N46: =M46*$B$15 -> 4725 | O46: =MAX($B$30*(1-$B$10)-L46,0) -> 1601.04 | P46: =IFERROR(O46/$B$40,0) -> 1601.04 | Q46: =P46*$B$16 -> 12808.32 | R46: =I46+J46+N46+Q46 -> 40643.726
A47: M3 | B47: =INDEX($I$5:$I$16, 1+MOD(3-1,12)) -> 1.5 | C47: =MIN(C46*(1+$B$21), $B$22) -> 55.125 | D47: =C47*$B$23*$B$24*$B$39*B47 -> 82.6875 | E47: =MIN(D47, $F$38) -> 82.6875 | F47: =(($B$31*$F$34*$B$10) + ($B$32*$F$35*$B$10))*(1+$F$24)*B47 -> 660.1518 | G47: =MIN(F47, MAX($F$38-E47,0), $F$25*$F$38) -> 529.5745 | H47: =IFERROR(($F$42*E47 + $F$41*G47)/(E47+G47),0) -> 35.888798 | I47: =(E47+G47)*H47 -> 21973.347 | J47: =H47*(E47+G47)*$F$12 -> 1098.6674 | K47: =C47*B25*B40*B47 -> 4961.25 | L47: =MIN(K47, $B$30*(1-$B$10)) -> 2546.04 | M47: =IFERROR(L47/$B$40,0) -> 2546.04 | N47: =M47*$B$15 -> 12730.2 | O47: =MAX($B$30*(1-$B$10)-L47,0) -> 0 | P47: =IFERROR(O47/$B$40,0) -> 0 | Q47: =P47*$B$16 -> 0 | R47: =I47+J47+N47+Q47 -> 35802.215
A48: M4 | B48: =INDEX($I$5:$I$16, 1+MOD(4-1,12)) -> 1.2 | C48: =MIN(C47*(1+$B$21), $B$22) -> 57.88125 | D48: =C48*$B$23*$B$24*$B$39*B48 -> 69.4575 | E48: =MIN(D48, $F$38) -> 69.4575 | F48: =(($B$31*$F$34*$B$10) + ($B$32*$F$35*$B$10))*(1+$F$24)*B48 -> 528.12144 | G48: =MIN(F48, MAX($F$38-E48,0), $F$25*$F$38) -> 528.12144 | H48: =IFERROR(($F$42*E48 + $F$41*G48)/(E48+G48),0) -> 36.063565 | I48: =(E48+G48)*H48 -> 21550.827 | J48: =H48*(E48+G48)*$F$12 -> 1077.5413 | K48: =C48*B25*B40*B48 -> 4167.45 | L48: =MIN(K48, $B$30*(1-$B$10)) -> 2546.04 | M48: =IFERROR(L48/$B$40,0) -> 2546.04 | N48: =M48*$B$15 -> 12730.2 | O48: =MAX($B$30*(1-$B$10)-L48,0) -> 0 | P48: =IFERROR(O48/$B$40,0) -> 0 | Q48: =P48*$B$16 -> 0 | R48: =I48+J48+N48+Q48 -> 35358.568
A49: M5 | B49: =INDEX($I$5:$I$16, 1+MOD(5-1,12)) -> 1 | C49: =MIN(C48*(1+$B$21), $B$22) -> 60.775313 | D49: =C49*$B$23*$B$24*$B$39*B49 -> 60.775313 | E49: =MIN(D49, $F$38) -> 60.775313 | F49: =(($B$31*$F$34*$B$10) + ($B$32*$F$35*$B$10))*(1+$F$24)*B49 -> 440.1012 | G49: =MIN(F49, MAX($F$38-E49,0), $F$25*$F$38) -> 440.1012 | H49: =IFERROR(($F$42*E49 + $F$41*G49)/(E49+G49),0) -> 36.016148 | I49: =(E49+G49)*H49 -> 18039.643 | J49: =H49*(E49+G49)*$F$12 -> 901.98213 | K49: =C49*B25*B40*B49 -> 3646.5188 | L49: =MIN(K49, $B$30*(1-$B$10)) -> 2546.04 | M49: =IFERROR(L49/$B$40,0) -> 2546.04 | N49: =M49*$B$15 -> 12730.2 | O49: =MAX($B$30*(1-$B$10)-L49,0) -> 0 | P49: =IFERROR(O49/$B$40,0) -> 0 | Q49: =P49*$B$16 -> 0 | R49: =I49+J49+N49+Q49 -> 31671.825
A50: M6 | B50: =INDEX($I$5:$I$16, 1+MOD(6-1,12)) -> 0.8 | C50: =MIN(C49*(1+$B$21), $B$22) -> 63.814078 | D50: =C50*$B$23*$B$24*$B$39*B50 -> 51.051263 | E50: =MIN(D50, $F$38) -> 51.051263 | F50: =(($B$31*$F$34*$B$10) + ($B$32*$F$35*$B$10))*(1+$F$24)*B50 -> 352.08096 | G50: =MIN(F50, MAX($F$38-E50,0), $F$25*$F$38) -> 352.08096 | H50: =IFERROR(($F$42*E50 + $F$41*G50)/(E50+G50),0) -> 35.966947 | I50: =(E50+G50)*H50 -> 14499.435 | J50: =H50*(E50+G50)*$F$12 -> 724.97176 | K50: =C50*B25*B40*B50 -> 3063.0758 | L50: =MIN(K50, $B$30*(1-$B$10)) -> 2546.04 | M50: =IFERROR(L50/$B$40,0) -> 2546.04 | N50: =M50*$B$15 -> 12730.2 | O50: =MAX($B$30*(1-$B$10)-L50,0) -> 0 | P50: =IFERROR(O50/$B$40,0) -> 0 | Q50: =P50*$B$16 -> 0 | R50: =I50+J50+N50+Q50 -> 27954.607
A51: M7 | B51: =INDEX($I$5:$I$16, 1+MOD(7-1,12)) -> 0.8 | C51: =MIN(C50*(1+$B$21), $B$22) -> 67.004782 | D51: =C51*$B$23*$B$24*$B$39*B51 -> 53.603826 | E51: =MIN(D51, $F$38) -> 53.603826 | F51: =(($B$31*$F$34*$B$10) + ($B$32*$F$35*$B$10))*(1+$F$24)*B51 -> 352.08096 | G51: =MIN(F51, MAX($F$38-E51,0), $F$25*$F$38) -> 352.08096 | H51: =IFERROR(($F$42*E51 + $F$41*G51)/(E51+G51),0) -> 35.91592 | I51: =(E51+G51)*H51 -> 14570.542 | J51: =H51*(E51+G51)*$F$12 -> 728.52711 | K51: =C51*B25*B40*B51 -> 3216.2295 | L51: =MIN(K51, $B$30*(1-$B$10)) -> 2546.04 | M51: =IFERROR(L51/$B$40,0) -> 2546.04 | N51: =M51*$B$15 -> 12730.2 | O51: =MAX($B$30*(1-$B$10)-L51,0) -> 0 | P51: =IFERROR(O51/$B$40,0) -> 0 | Q51: =P51*$B$16 -> 0 | R51: =I51+J51+N51+Q51 -> 28029.269
A52: M8 | B52: =INDEX($I$5:$I$16, 1+MOD(8-1,12)) -> 0.8 | C52: =MIN(C51*(1+$B$21), $B$22) -> 70.355021 | D52: =C52*$B$23*$B$24*$B$39*B52 -> 56.284017 | E52: =MIN(D52, $F$38) -> 56.284017 | F52: =(($B$31*$F$34*$B$10) + ($B$32*$F$35*$B$10))*(1+$F$24)*B52 -> 352.08096 | G52: =MIN(F52, MAX($F$38-E52,0), $F$25*$F$38) -> 352.08096 | H52: =IFERROR(($F$42*E52 + $F$41*G52)/(E52+G52),0) -> 35.863028 | I52: =(E52+G52)*H52 -> 14645.205 | J52: =H52*(E52+G52)*$F$12 -> 732.26023 | K52: =C52*B25*B40*B52 -> 3377.041 | L52: =MIN(K52, $B$30*(1-$B$10)) -> 2546.04 | M52: =IFERROR(L52/$B$40,0) -> 2546.04 | N52: =M52*$B$15 -> 12730.2 | O52: =MAX($B$30*(1-$B$10)-L52,0) -> 0 | P52: =IFERROR(O52/$B$40,0) -> 0 | Q52: =P52*$B$16 -> 0 | R52: =I52+J52+N52+Q52 -> 28107.665
A53: M9 | B53: =INDEX($I$5:$I$16, 1+MOD(9-1,12)) -> 1 | C53: =MIN(C52*(1+$B$21), $B$22) -> 73.872772 | D53: =C53*$B$23*$B$24*$B$39*B53 -> 73.872772 | E53: =MIN(D53, $F$38) -> 73.872772 | F53: =(($B$31*$F$34*$B$10) + ($B$32*$F$35*$B$10))*(1+$F$24)*B53 -> 440.1012 | G53: =MIN(F53, MAX($F$38-E53,0), $F$25*$F$38) -> 440.1012 | H53: =IFERROR(($F$42*E53 + $F$41*G53)/(E53+G53),0) -> 35.808234 | I53: =(E53+G53)*H53 -> 18404.5 | J53: =H53*(E53+G53)*$F$12 -> 920.22502 | K53: =C53*B25*B40*B53 -> 4432.3663 | L53: =MIN(K53, $B$30*(1-$B$10)) -> 2546.04 | M53: =IFERROR(L53/$B$40,0) -> 2546.04 | N53: =M53*$B$15 -> 12730.2 | O53: =MAX($B$30*(1-$B$10)-L53,0) -> 0 | P53: =IFERROR(O53/$B$40,0) -> 0 | Q53: =P53*$B$16 -> 0 | R53: =I53+J53+N53+Q53 -> 32054.925
A54: M10 | B54: =INDEX($I$5:$I$16, 1+MOD(10-1,12)) -> 1.2 | C54: =MIN(C53*(1+$B$21), $B$22) -> 77.566411 | D54: =C54*$B$23*$B$24*$B$39*B54 -> 93.079693 | E54: =MIN(D54, $F$38) -> 93.079693 | F54: =(($B$31*$F$34*$B$10) + ($B$32*$F$35*$B$10))*(1+$F$24)*B54 -> 528.12144 | G54: =MIN(F54, MAX($F$38-E54,0), $F$25*$F$38) -> 519.18231 | H54: =IFERROR(($F$42*E54 + $F$41*G54)/(E54+G54),0) -> 35.731188 | I54: =(E54+G54)*H54 -> 21876.849 | J54: =H54*(E54+G54)*$F$12 -> 1093.8424 | K54: =C54*B25*B40*B54 -> 5584.7816 | L54: =MIN(K54, $B$30*(1-$B$10)) -> 2546.04 | M54: =IFERROR(L54/$B$40,0) -> 2546.04 | N54: =M54*$B$15 -> 12730.2 | O54: =MAX($B$30*(1-$B$10)-L54,0) -> 0 | P54: =IFERROR(O54/$B$40,0) -> 0 | Q54: =P54*$B$16 -> 0 | R54: =I54+J54+N54+Q54 -> 35700.891
A55: M11 | B55: =INDEX($I$5:$I$16, 1+MOD(11-1,12)) -> 1.5 | C55: =MIN(C54*(1+$B$21), $B$22) -> 81.444731 | D55: =C55*$B$23*$B$24*$B$39*B55 -> 122.1671 | E55: =MIN(D55, $F$38) -> 122.1671 | F55: =(($B$31*$F$34*$B$10) + ($B$32*$F$35*$B$10))*(1+$F$24)*B55 -> 660.1518 | G55: =MIN(F55, MAX($F$38-E55,0), $F$25*$F$38) -> 490.0949 | H55: =IFERROR(($F$42*E55 + $F$41*G55)/(E55+G55),0) -> 35.290041 | I55: =(E55+G55)*H55 -> 21606.751 | J55: =H55*(E55+G55)*$F$12 -> 1080.3376 | K55: =C55*B25*B40*B55 -> 7330.0258 | L55: =MIN(K55, $B$30*(1-$B$10)) -> 2546.04 | M55: =IFERROR(L55/$B$40,0) -> 2546.04 | N55: =M55*$B$15 -> 12730.2 | O55: =MAX($B$30*(1-$B$10)-L55,0) -> 0 | P55: =IFERROR(O55/$B$40,0) -> 0 | Q55: =P55*$B$16 -> 0 | R55: =I55+J55+N55+Q55 -> 35417.289
A56: M12 | B56: =INDEX($I$5:$I$16, 1+MOD(12-1,12)) -> 2 | C56: =MIN(C55*(1+$B$21), $B$22) -> 85.516968 | D56: =C56*$B$23*$B$24*$B$39*B56 -> 171.03394 | E56: =MIN(D56, $F$38) -> 171.03394 | F56: =(($B$31*$F$34*$B$10) + ($B$32*$F$35*$B$10))*(1+$F$24)*B56 -> 880.2024 | G56: =MIN(F56, MAX($F$38-E56,0), $F$25*$F$38) -> 441.22806 | H56: =IFERROR(($F$42*E56 + $F$41*G56)/(E56+G56),0) -> 34.548915 | I56: =(E56+G56)*H56 -> 21152.988 | J56: =H56*(E56+G56)*$F$12 -> 1057.6494 | K56: =C56*B25*B40*B56 -> 10262.036 | L56: =MIN(K56, $B$30*(1-$B$10)) -> 2546.04 | M56: =IFERROR(L56/$B$40,0) -> 2546.04 | N56: =M56*$B$15 -> 12730.2 | O56: =MAX($B$30*(1-$B$10)-L56,0) -> 0 | P56: =IFERROR(O56/$B$40,0) -> 0 | Q56: =P56*$B$16 -> 0 | R56: =I56+J56+N56+Q56 -> 34940.837
A57: M13 | B57: =INDEX($I$5:$I$16, 1+MOD(13-1,12)) -> 2 | C57: =MIN(C56*(1+$B$21), $B$22) -> 89.792816 | D57: =C57*$B$23*$B$24*$B$39*B57 -> 179.58563 | E57: =MIN(D57, $F$38) -> 179.58563 | F57: =(($B$31*$F$34*$B$10) + ($B$32*$F$35*$B$10))*(1+$F$24)*B57 -> 880.2024 | G57: =MIN(F57, MAX($F$38-E57,0), $F$25*$F$38) -> 432.67637 | H57: =IFERROR(($F$42*E57 + $F$41*G57)/(E57+G57),0) -> 34.419218 | I57: =(E57+G57)*H57 -> 21073.579 | J57: =H57*(E57+G57)*$F$12 -> 1053.679 | K57: =C57*B25*B40*B57 -> 10775.138 | L57: =MIN(K57, $B$30*(1-$B$10)) -> 2546.04 | M57: =IFERROR(L57/$B$40,0) -> 2546.04 | N57: =M57*$B$15 -> 12730.2 | O57: =MAX($B$30*(1-$B$10)-L57,0) -> 0 | P57: =IFERROR(O57/$B$40,0) -> 0 | Q57: =P57*$B$16 -> 0 | R57: =I57+J57+N57+Q57 -> 34857.458
A58: M14 | B58: =INDEX($I$5:$I$16, 1+MOD(14-1,12)) -> 1.5 | C58: =MIN(C57*(1+$B$21), $B$22) -> 94.282457 | D58: =C58*$B$23*$B$24*$B$39*B58 -> 141.42369 | E58: =MIN(D58, $F$38) -> 141.42369 | F58: =(($B$31*$F$34*$B$10) + ($B$32*$F$35*$B$10))*(1+$F$24)*B58 -> 660.1518 | G58: =MIN(F58, MAX($F$38-E58,0), $F$25*$F$38) -> 470.83831 | H58: =IFERROR(($F$42*E58 + $F$41*G58)/(E58+G58),0) -> 34.997991 | I58: =(E58+G58)*H58 -> 21427.94 | J58: =H58*(E58+G58)*$F$12 -> 1071.397 | K58: =C58*B25*B40*B58 -> 8485.4211 | L58: =MIN(K58, $B$30*(1-$B$10)) -> 2546.04 | M58: =IFERROR(L58/$B$40,0) -> 2546.04 | N58: =M58*$B$15 -> 12730.2 | O58: =MAX($B$30*(1-$B$10)-L58,0) -> 0 | P58: =IFERROR(O58/$B$40,0) -> 0 | Q58: =P58*$B$16 -> 0 | R58: =I58+J58+N58+Q58 -> 35229.537
A59: M15 | B59: =INDEX($I$5:$I$16, 1+MOD(15-1,12)) -> 1.5 | C59: =MIN(C58*(1+$B$21), $B$22) -> 98.99658 | D59: =C59*$B$23*$B$24*$B$39*B59 -> 148.49487 | E59: =MIN(D59, $F$38) -> 148.49487 | F59: =(($B$31*$F$34*$B$10) + ($B$32*$F$35*$B$10))*(1+$F$24)*B59 -> 660.1518 | G59: =MIN(F59, MAX($F$38-E59,0), $F$25*$F$38) -> 463.76713 | H59: =IFERROR(($F$42*E59 + $F$41*G59)/(E59+G59),0) -> 34.890748 | I59: =(E59+G59)*H59 -> 21362.279 | J59: =H59*(E59+G59)*$F$12 -> 1068.114 | K59: =C59*B25*B40*B59 -> 8909.6922 | L59: =MIN(K59, $B$30*(1-$B$10)) -> 2546.04 | M59: =IFERROR(L59/$B$40,0) -> 2546.04 | N59: =M59*$B$15 -> 12730.2 | O59: =MAX($B$30*(1-$B$10)-L59,0) -> 0 | P59: =IFERROR(O59/$B$40,0) -> 0 | Q59: =P59*$B$16 -> 0 | R59: =I59+J59+N59+Q59 -> 35160.593
A60: M16 | B60: =INDEX($I$5:$I$16, 1+MOD(16-1,12)) -> 1.2 | C60: =MIN(C59*(1+$B$21), $B$22) -> 103.94641 | D60: =C60*$B$23*$B$24*$B$39*B60 -> 124.73569 | E60: =MIN(D60, $F$38) -> 124.73569 | F60: =(($B$31*$F$34*$B$10) + ($B$32*$F$35*$B$10))*(1+$F$24)*B60 -> 528.12144 | G60: =MIN(F60, MAX($F$38-E60,0), $F$25*$F$38) -> 487.52631 | H60: =IFERROR(($F$42*E60 + $F$41*G60)/(E60+G60),0) -> 35.251085 | I60: =(E60+G60)*H60 -> 21582.9 | J60: =H60*(E60+G60)*$F$12 -> 1079.145 | K60: =C60*B25*B40*B60 -> 7484.1414 | L60: =MIN(K60, $B$30*(1-$B$10)) -> 2546.04 | M60: =IFERROR(L60/$B$40,0) -> 2546.04 | N60: =M60*$B$15 -> 12730.2 | O60: =MAX($B$30*(1-$B$10)-L60,0) -> 0 | P60: =IFERROR(O60/$B$40,0) -> 0 | Q60: =P60*$B$16 -> 0 | R60: =I60+J60+N60+Q60 -> 35392.245
A61: M17 | B61: =INDEX($I$5:$I$16, 1+MOD(17-1,12)) -> 1 | C61: =MIN(C60*(1+$B$21), $B$22) -> 109.14373 | D61: =C61*$B$23*$B$24*$B$39*B61 -> 109.14373 | E61: =MIN(D61, $F$38) -> 109.14373 | F61: =(($B$31*$F$34*$B$10) + ($B$32*$F$35*$B$10))*(1+$F$24)*B61 -> 440.1012 | G61: =MIN(F61, MAX($F$38-E61,0), $F$25*$F$38) -> 440.1012 | H61: =IFERROR(($F$42*E61 + $F$41*G61)/(E61+G61),0) -> 35.297638 | I61: =(E61+G61)*H61 -> 19387.048 | J61: =H61*(E61+G61)*$F$12 -> 969.35242 | K61: =C61*B25*B40*B61 -> 6548.6238 | L61: =MIN(K61, $B$30*(1-$B$10)) -> 2546.04 | M61: =IFERROR(L61/$B$40,0) -> 2546.04 | N61: =M61*$B$15 -> 12730.2 | O61: =MAX($B$30*(1-$B$10)-L61,0) -> 0 | P61: =IFERROR(O61/$B$40,0) -> 0 | Q61: =P61*$B$16 -> 0 | R61: =I61+J61+N61+Q61 -> 33086.601
A62: M18 | B62: =INDEX($I$5:$I$16, 1+MOD(18-1,12)) -> 0.8 | C62: =MIN(C61*(1+$B$21), $B$22) -> 114.60092 | D62: =C62*$B$23*$B$24*$B$39*B62 -> 91.680733 | E62: =MIN(D62, $F$38) -> 91.680733 | F62: =(($B$31*$F$34*$B$10) + ($B$32*$F$35*$B$10))*(1+$F$24)*B62 -> 352.08096 | G62: =MIN(F62, MAX($F$38-E62,0), $F$25*$F$38) -> 352.08096 | H62: =IFERROR(($F$42*E62 + $F$41*G62)/(E62+G62),0) -> 35.224438 | I62: =(E62+G62)*H62 -> 15631.256 | J62: =H62*(E62+G62)*$F$12 -> 781.5628 | K62: =C62*B25*B40*B62 -> 5500.844 | L62: =MIN(K62, $B$30*(1-$B$10)) -> 2546.04 | M62: =IFERROR(L62/$B$40,0) -> 2546.04 | N62: =M62*$B$15 -> 12730.2 | O62: =MAX($B$30*(1-$B$10)-L62,0) -> 0 | P62: =IFERROR(O62/$B$40,0) -> 0 | Q62: =P62*$B$16 -> 0 | R62: =I62+J62+N62+Q62 -> 29143.019
A63: M19 | B63: =INDEX($I$5:$I$16, 1+MOD(19-1,12)) -> 0.8 | C63: =MIN(C62*(1+$B$21), $B$22) -> 120.33096 | D63: =C63*$B$23*$B$24*$B$39*B63 -> 96.264769 | E63: =MIN(D63, $F$38) -> 96.264769 | F63: =(($B$31*$F$34*$B$10) + ($B$32*$F$35*$B$10))*(1+$F$24)*B63 -> 352.08096 | G63: =MIN(F63, MAX($F$38-E63,0), $F$25*$F$38) -> 352.08096 | H63: =IFERROR(($F$42*E63 + $F$41*G63)/(E63+G63),0) -> 35.149112 | I63: =(E63+G63)*H63 -> 15758.954 | J63: =H63*(E63+G63)*$F$12 -> 787.94771 | K63: =C63*B25*B40*B63 -> 5775.8862 | L63: =MIN(K63, $B$30*(1-$B$10)) -> 2546.04 | M63: =IFERROR(L63/$B$40,0) -> 2546.04 | N63: =M63*$B$15 -> 12730.2 | O63: =MAX($B$30*(1-$B$10)-L63,0) -> 0 | P63: =IFERROR(O63/$B$40,0) -> 0 | Q63: =P63*$B$16 -> 0 | R63: =I63+J63+N63+Q63 -> 29277.102
A64: M20 | B64: =INDEX($I$5:$I$16, 1+MOD(20-1,12)) -> 0.8 | C64: =MIN(C63*(1+$B$21), $B$22) -> 126.34751 | D64: =C64*$B$23*$B$24*$B$39*B64 -> 101.07801 | E64: =MIN(D64, $F$38) -> 101.07801 | F64: =(($B$31*$F$34*$B$10) + ($B$32*$F$35*$B$10))*(1+$F$24)*B64 -> 352.08096 | G64: =MIN(F64, MAX($F$38-E64,0), $F$25*$F$38) -> 352.08096 | H64: =IFERROR(($F$42*E64 + $F$41*G64)/(E64+G64),0) -> 35.07166 | I64: =(E64+G64)*H64 -> 15893.037 | J64: =H64*(E64+G64)*$F$12 -> 794.65187 | K64: =C64*B25*B40*B64 -> 6064.6805 | L64: =MIN(K64, $B$30*(1-$B$10)) -> 2546.04 | M64: =IFERROR(L64/$B$40,0) -> 2546.04 | N64: =M64*$B$15 -> 12730.2 | O64: =MAX($B$30*(1-$B$10)-L64,0) -> 0 | P64: =IFERROR(O64/$B$40,0) -> 0 | Q64: =P64*$B$16 -> 0 | R64: =I64+J64+N64+Q64 -> 29417.889
A65: M21 | B65: =INDEX($I$5:$I$16, 1+MOD(21-1,12)) -> 1 | C65: =MIN(C64*(1+$B$21), $B$22) -> 132.66489 | D65: =C65*$B$23*$B$24*$B$39*B65 -> 132.66489 | E65: =MIN(D65, $F$38) -> 132.66489 | F65: =(($B$31*$F$34*$B$10) + ($B$32*$F$35*$B$10))*(1+$F$24)*B65 -> 440.1012 | G65: =MIN(F65, MAX($F$38-E65,0), $F$25*$F$38) -> 440.1012 | H65: =IFERROR(($F$42*E65 + $F$41*G65)/(E65+G65),0) -> 34.992087 | I65: =(E65+G65)*H65 -> 20042.281 | J65: =H65*(E65+G65)*$F$12 -> 1002.114 | K65: =C65*B25*B40*B65 -> 7959.8931 | L65: =MIN(K65, $B$30*(1-$B$10)) -> 2546.04 | M65: =IFERROR(L65/$B$40,0) -> 2546.04 | N65: =M65*$B$15 -> 12730.2 | O65: =MAX($B$30*(1-$B$10)-L65,0) -> 0 | P65: =IFERROR(O65/$B$40,0) -> 0 | Q65: =P65*$B$16 -> 0 | R65: =I65+J65+N65+Q65 -> 33774.595
A66: M22 | B66: =INDEX($I$5:$I$16, 1+MOD(22-1,12)) -> 1.2 | C66: =MIN(C65*(1+$B$21), $B$22) -> 139.29813 | D66: =C66*$B$23*$B$24*$B$39*B66 -> 167.15776 | E66: =MIN(D66, $F$38) -> 167.15776 | F66: =(($B$31*$F$34*$B$10) + ($B$32*$F$35*$B$10))*(1+$F$24)*B66 -> 528.12144 | G66: =MIN(F66, MAX($F$38-E66,0), $F$25*$F$38) -> 445.10424 | H66: =IFERROR(($F$42*E66 + $F$41*G66)/(E66+G66),0) -> 34.607702 | I66: =(E66+G66)*H66 -> 21188.981 | J66: =H66*(E66+G66)*$F$12 -> 1059.449 | K66: =C66*B25*B40*B66 -> 10029.465 | L66: =MIN(K66, $B$30*(1-$B$10)) -> 2546.04 | M66: =IFERROR(L66/$B$40,0) -> 2546.04 | N66: =M66*$B$15 -> 12730.2 | O66: =MAX($B$30*(1-$B$10)-L66,0) -> 0 | P66: =IFERROR(O66/$B$40,0) -> 0 | Q66: =P66*$B$16 -> 0 | R66: =I66+J66+N66+Q66 -> 34978.63
A67: M23 | B67: =INDEX($I$5:$I$16, 1+MOD(23-1,12)) -> 1.5 | C67: =MIN(C66*(1+$B$21), $B$22) -> 146.26304 | D67: =C67*$B$23*$B$24*$B$39*B67 -> 219.39455 | E67: =MIN(D67, $F$38) -> 219.39455 | F67: =(($B$31*$F$34*$B$10) + ($B$32*$F$35*$B$10))*(1+$F$24)*B67 -> 660.1518 | G67: =MIN(F67, MAX($F$38-E67,0), $F$25*$F$38) -> 392.86745 | H67: =IFERROR(($F$42*E67 + $F$41*G67)/(E67+G67),0) -> 33.815466 | I67: =(E67+G67)*H67 -> 20703.925 | J67: =H67*(E67+G67)*$F$12 -> 1035.1962 | K67: =C67*B25*B40*B67 -> 13163.673 | L67: =MIN(K67, $B$30*(1-$B$10)) -> 2546.04 | M67: =IFERROR(L67/$B$40,0) -> 2546.04 | N67: =M67*$B$15 -> 12730.2 | O67: =MAX($B$30*(1-$B$10)-L67,0) -> 0 | P67: =IFERROR(O67/$B$40,0) -> 0 | Q67: =P67*$B$16 -> 0 | R67: =I67+J67+N67+Q67 -> 34469.321
A68: M24 | B68: =INDEX($I$5:$I$16, 1+MOD(24-1,12)) -> 2 | C68: =MIN(C67*(1+$B$21), $B$22) -> 153.57619 | D68: =C68*$B$23*$B$24*$B$39*B68 -> 307.15238 | E68: =MIN(D68, $F$38) -> 307.15238 | F68: =(($B$31*$F$34*$B$10) + ($B$32*$F$35*$B$10))*(1+$F$24)*B68 -> 880.2024 | G68: =MIN(F68, MAX($F$38-E68,0), $F$25*$F$38) -> 305.10962 | H68: =IFERROR(($F$42*E68 + $F$41*G68)/(E68+G68),0) -> 32.48451 | I68: =(E68+G68)*H68 -> 19889.031 | J68: =H68*(E68+G68)*$F$12 -> 994.45154 | K68: =C68*B25*B40*B68 -> 18429.143 | L68: =MIN(K68, $B$30*(1-$B$10)) -> 2546.04 | M68: =IFERROR(L68/$B$40,0) -> 2546.04 | N68: =M68*$B$15 -> 12730.2 | O68: =MAX($B$30*(1-$B$10)-L68,0) -> 0 | P68: =IFERROR(O68/$B$40,0) -> 0 | Q68: =P68*$B$16 -> 0 | R68: =I68+J68+N68+Q68 -> 33613.682
A69: M25 | B69: =INDEX($I$5:$I$16, 1+MOD(25-1,12)) -> 2 | C69: =MIN(C68*(1+$B$21), $B$22) -> 161.255 | D69: =C69*$B$23*$B$24*$B$39*B69 -> 322.50999 | E69: =MIN(D69, $F$38) -> 322.50999 | F69: =(($B$31*$F$34*$B$10) + ($B$32*$F$35*$B$10))*(1+$F$24)*B69 -> 880.2024 | G69: =MIN(F69, MAX($F$38-E69,0), $F$25*$F$38) -> 289.75201 | H69: =IFERROR(($F$42*E69 + $F$41*G69)/(E69+G69),0) -> 32.251592 | I69: =(E69+G69)*H69 -> 19746.424 | J69: =H69*(E69+G69)*$F$12 -> 987.32122 | K69: =C69*B25*B40*B69 -> 19350.6 | L69: =MIN(K69, $B$30*(1-$B$10)) -> 2546.04 | M69: =IFERROR(L69/$B$40,0) -> 2546.04 | N69: =M69*$B$15 -> 12730.2 | O69: =MAX($B$30*(1-$B$10)-L69,0) -> 0 | P69: =IFERROR(O69/$B$40,0) -> 0 | Q69: =P69*$B$16 -> 0 | R69: =I69+J69+N69+Q69 -> 33463.946
A70: M26 | B70: =INDEX($I$5:$I$16, 1+MOD(26-1,12)) -> 1.5 | C70: =MIN(C69*(1+$B$21), $B$22) -> 169.31775 | D70: =C70*$B$23*$B$24*$B$39*B70 -> 253.97662 | E70: =MIN(D70, $F$38) -> 253.97662 | F70: =(($B$31*$F$34*$B$10) + ($B$32*$F$35*$B$10))*(1+$F$24)*B70 -> 660.1518 | G70: =MIN(F70, MAX($F$38-E70,0), $F$25*$F$38) -> 358.28538 | H70: =IFERROR(($F$42*E70 + $F$41*G70)/(E70+G70),0) -> 33.290986 | I70: =(E70+G70)*H70 -> 20382.806 | J70: =H70*(E70+G70)*$F$12 -> 1019.1403 | K70: =C70*B25*B40*B70 -> 15238.597 | L70: =MIN(K70, $B$30*(1-$B$10)) -> 2546.04 | M70: =IFERROR(L70/$B$40,0) -> 2546.04 | N70: =M70*$B$15 -> 12730.2 | O70: =MAX($B$30*(1-$B$10)-L70,0) -> 0 | P70: =IFERROR(O70/$B$40,0) -> 0 | Q70: =P70*$B$16 -> 0 | R70: =I70+J70+N70+Q70 -> 34132.146
A71: M27 | B71: =INDEX($I$5:$I$16, 1+MOD(27-1,12)) -> 1.5 | C71: =MIN(C70*(1+$B$21), $B$22) -> 177.78363 | D71: =C71*$B$23*$B$24*$B$39*B71 -> 266.67545 | E71: =MIN(D71, $F$38) -> 266.67545 | F71: =(($B$31*$F$34*$B$10) + ($B$32*$F$35*$B$10))*(1+$F$24)*B71 -> 660.1518 | G71: =MIN(F71, MAX($F$38-E71,0), $F$25*$F$38) -> 345.58655 | H71: =IFERROR(($F$42*E71 + $F$41*G71)/(E71+G71),0) -> 33.098392 | I71: =(E71+G71)*H71 -> 20264.888 | J71: =H71*(E71+G71)*$F$12 -> 1013.2444 | K71: =C71*B25*B40*B71 -> 16000.527 | L71: =MIN(K71, $B$30*(1-$B$10)) -> 2546.04 | M71: =IFERROR(L71/$B$40,0) -> 2546.04 | N71: =M71*$B$15 -> 12730.2 | O71: =MAX($B$30*(1-$B$10)-L71,0) -> 0 | P71: =IFERROR(O71/$B$40,0) -> 0 | Q71: =P71*$B$16 -> 0 | R71: =I71+J71+N71+Q71 -> 34008.332
A72: M28 | B72: =INDEX($I$5:$I$16, 1+MOD(28-1,12)) -> 1.2 | C72: =MIN(C71*(1+$B$21), $B$22) -> 186.67282 | D72: =C72*$B$23*$B$24*$B$39*B72 -> 224.00738 | E72: =MIN(D72, $F$38) -> 224.00738 | F72: =(($B$31*$F$34*$B$10) + ($B$32*$F$35*$B$10))*(1+$F$24)*B72 -> 528.12144 | G72: =MIN(F72, MAX($F$38-E72,0), $F$25*$F$38) -> 388.25462 | H72: =IFERROR(($F$42*E72 + $F$41*G72)/(E72+G72),0) -> 33.745507 | I72: =(E72+G72)*H72 -> 20661.091 | J72: =H72*(E72+G72)*$F$12 -> 1033.0546 | K72: =C72*B25*B40*B72 -> 13440.443 | L72: =MIN(K72, $B$30*(1-$B$10)) -> 2546.04 | M72: =IFERROR(L72/$B$40,0) -> 2546.04 | N72: =M72*$B$15 -> 12730.2 | O72: =MAX($B$30*(1-$B$10)-L72,0) -> 0 | P72: =IFERROR(O72/$B$40,0) -> 0 | Q72: =P72*$B$16 -> 0 | R72: =I72+J72+N72+Q72 -> 34424.346
A73: M29 | B73: =INDEX($I$5:$I$16, 1+MOD(29-1,12)) -> 1 | C73: =MIN(C72*(1+$B$21), $B$22) -> 196.00646 | D73: =C73*$B$23*$B$24*$B$39*B73 -> 196.00646 | E73: =MIN(D73, $F$38) -> 196.00646 | F73: =(($B$31*$F$34*$B$10) + ($B$32*$F$35*$B$10))*(1+$F$24)*B73 -> 440.1012 | G73: =MIN(F73, MAX($F$38-E73,0), $F$25*$F$38) -> 416.25554 | H73: =IFERROR(($F$42*E73 + $F$41*G73)/(E73+G73),0) -> 34.170176 | I73: =(E73+G73)*H73 -> 20921.1 | J73: =H73*(E73+G73)*$F$12 -> 1046.055 | K73: =C73*B25*B40*B73 -> 11760.387 | L73: =MIN(K73, $B$30*(1-$B$10)) -> 2546.04 | M73: =IFERROR(L73/$B$40,0) -> 2546.04 | N73: =M73*$B$15 -> 12730.2 | O73: =MAX($B$30*(1-$B$10)-L73,0) -> 0 | P73: =IFERROR(O73/$B$40,0) -> 0 | Q73: =P73*$B$16 -> 0 | R73: =I73+J73+N73+Q73 -> 34697.355
A74: M30 | B74: =INDEX($I$5:$I$16, 1+MOD(30-1,12)) -> 0.8 | C74: =MIN(C73*(1+$B$21), $B$22) -> 205.80678 | D74: =C74*$B$23*$B$24*$B$39*B74 -> 164.64542 | E74: =MIN(D74, $F$38) -> 164.64542 | F74: =(($B$31*$F$34*$B$10) + ($B$32*$F$35*$B$10))*(1+$F$24)*B74 -> 352.08096 | G74: =MIN(F74, MAX($F$38-E74,0), $F$25*$F$38) -> 352.08096 | H74: =IFERROR(($F$42*E74 + $F$41*G74)/(E74+G74),0) -> 34.184134 | I74: =(E74+G74)*H74 -> 17663.844 | J74: =H74*(E74+G74)*$F$12 -> 883.19219 | K74: =C74*B25*B40*B74 -> 9878.7254 | L74: =MIN(K74, $B$30*(1-$B$10)) -> 2546.04 | M74: =IFERROR(L74/$B$40,0) -> 2546.04 | N74: =M74*$B$15 -> 12730.2 | O74: =MAX($B$30*(1-$B$10)-L74,0) -> 0 | P74: =IFERROR(O74/$B$40,0) -> 0 | Q74: =P74*$B$16 -> 0 | R74: =I74+J74+N74+Q74 -> 31277.236
A75: M31 | B75: =INDEX($I$5:$I$16, 1+MOD(31-1,12)) -> 0.8 | C75: =MIN(C74*(1+$B$21), $B$22) -> 216.09712 | D75: =C75*$B$23*$B$24*$B$39*B75 -> 172.8777 | E75: =MIN(D75, $F$38) -> 172.8777 | F75: =(($B$31*$F$34*$B$10) + ($B$32*$F$35*$B$10))*(1+$F$24)*B75 -> 352.08096 | G75: =MIN(F75, MAX($F$38-E75,0), $F$25*$F$38) -> 352.08096 | H75: =IFERROR(($F$42*E75 + $F$41*G75)/(E75+G75),0) -> 34.084916 | I75: =(E75+G75)*H75 -> 17893.171 | J75: =H75*(E75+G75)*$F$12 -> 894.65857 | K75: =C75*B25*B40*B75 -> 10372.662 | L75: =MIN(K75, $B$30*(1-$B$10)) -> 2546.04 | M75: =IFERROR(L75/$B$40,0) -> 2546.04 | N75: =M75*$B$15 -> 12730.2 | O75: =MAX($B$30*(1-$B$10)-L75,0) -> 0 | P75: =IFERROR(O75/$B$40,0) -> 0 | Q75: =P75*$B$16 -> 0 | R75: =I75+J75+N75+Q75 -> 31518.03
A76: M32 | B76: =INDEX($I$5:$I$16, 1+MOD(32-1,12)) -> 0.8 | C76: =MIN(C75*(1+$B$21), $B$22) -> 226.90197 | D76: =C76*$B$23*$B$24*$B$39*B76 -> 181.52158 | E76: =MIN(D76, $F$38) -> 181.52158 | F76: =(($B$31*$F$34*$B$10) + ($B$32*$F$35*$B$10))*(1+$F$24)*B76 -> 352.08096 | G76: =MIN(F76, MAX($F$38-E76,0), $F$25*$F$38) -> 352.08096 | H76: =IFERROR(($F$42*E76 + $F$41*G76)/(E76+G76),0) -> 33.984031 | I76: =(E76+G76)*H76 -> 18133.965 | J76: =H76*(E76+G76)*$F$12 -> 906.69827 | K76: =C76*B25*B40*B76 -> 10891.295 | L76: =MIN(K76, $B$30*(1-$B$10)) -> 2546.04 | M76: =IFERROR(L76/$B$40,0) -> 2546.04 | N76: =M76*$B$15 -> 12730.2 | O76: =MAX($B$30*(1-$B$10)-L76,0) -> 0 | P76: =IFERROR(O76/$B$40,0) -> 0 | Q76: =P76*$B$16 -> 0 | R76: =I76+J76+N76+Q76 -> 31770.864
A77: M33 | B77: =INDEX($I$5:$I$16, 1+MOD(33-1,12)) -> 1 | C77: =MIN(C76*(1+$B$21), $B$22) -> 238.24707 | D77: =C77*$B$23*$B$24*$B$39*B77 -> 238.24707 | E77: =MIN(D77, $F$38) -> 238.24707 | F77: =(($B$31*$F$34*$B$10) + ($B$32*$F$35*$B$10))*(1+$F$24)*B77 -> 440.1012 | G77: =MIN(F77, MAX($F$38-E77,0), $F$25*$F$38) -> 374.01493 | H77: =IFERROR(($F$42*E77 + $F$41*G77)/(E77+G77),0) -> 33.529544 | I77: =(E77+G77)*H77 -> 20528.866 | J77: =H77*(E77+G77)*$F$12 -> 1026.4433 | K77: =C77*B25*B40*B77 -> 14294.824 | L77: =MIN(K77, $B$30*(1-$B$10)) -> 2546.04 | M77: =IFERROR(L77/$B$40,0) -> 2546.04 | N77: =M77*$B$15 -> 12730.2 | O77: =MAX($B$30*(1-$B$10)-L77,0) -> 0 | P77: =IFERROR(O77/$B$40,0) -> 0 | Q77: =P77*$B$16 -> 0 | R77: =I77+J77+N77+Q77 -> 34285.509
A78: M34 | B78: =INDEX($I$5:$I$16, 1+MOD(34-1,12)) -> 1.2 | C78: =MIN(C77*(1+$B$21), $B$22) -> 250.15943 | D78: =C78*$B$23*$B$24*$B$39*B78 -> 300.19131 | E78: =MIN(D78, $F$38) -> 300.19131 | F78: =(($B$31*$F$34*$B$10) + ($B$32*$F$35*$B$10))*(1+$F$24)*B78 -> 528.12144 | G78: =MIN(F78, MAX($F$38-E78,0), $F$25*$F$38) -> 312.07069 | H78: =IFERROR(($F$42*E78 + $F$41*G78)/(E78+G78),0) -> 32.590083 | I78: =(E78+G78)*H78 -> 19953.669 | J78: =H78*(E78+G78)*$F$12 -> 997.68346 | K78: =C78*B25*B40*B78 -> 18011.479 | L78: =MIN(K78, $B$30*(1-$B$10)) -> 2546.04 | M78: =IFERROR(L78/$B$40,0) -> 2546.04 | N78: =M78*$B$15 -> 12730.2 | O78: =MAX($B$30*(1-$B$10)-L78,0) -> 0 | P78: =IFERROR(O78/$B$40,0) -> 0 | Q78: =P78*$B$16 -> 0 | R78: =I78+J78+N78+Q78 -> 33681.553
A79: M35 | B79: =INDEX($I$5:$I$16, 1+MOD(35-1,12)) -> 1.5 | C79: =MIN(C78*(1+$B$21), $B$22) -> 262.6674 | D79: =C79*$B$23*$B$24*$B$39*B79 -> 394.0011 | E79: =MIN(D79, $F$38) -> 394.0011 | F79: =(($B$31*$F$34*$B$10) + ($B$32*$F$35*$B$10))*(1+$F$24)*B79 -> 660.1518 | G79: =MIN(F79, MAX($F$38-E79,0), $F$25*$F$38) -> 218.2609 | H79: =IFERROR(($F$42*E79 + $F$41*G79)/(E79+G79),0) -> 31.167341 | I79: =(E79+G79)*H79 -> 19082.578 | J79: =H79*(E79+G79)*$F$12 -> 954.12892 | K79: =C79*B25*B40*B79 -> 23640.066 | L79: =MIN(K79, $B$30*(1-$B$10)) -> 2546.04 | M79: =IFERROR(L79/$B$40,0) -> 2546.04 | N79: =M79*$B$15 -> 12730.2 | O79: =MAX($B$30*(1-$B$10)-L79,0) -> 0 | P79: =IFERROR(O79/$B$40,0) -> 0 | Q79: =P79*$B$16 -> 0 | R79: =I79+J79+N79+Q79 -> 32766.907
A80: M36 | B80: =INDEX($I$5:$I$16, 1+MOD(36-1,12)) -> 2 | C80: =MIN(C79*(1+$B$21), $B$22) -> 275.80077 | D80: =C80*$B$23*$B$24*$B$39*B80 -> 551.60154 | E80: =MIN(D80, $F$38) -> 551.60154 | F80: =(($B$31*$F$34*$B$10) + ($B$32*$F$35*$B$10))*(1+$F$24)*B80 -> 880.2024 | G80: =MIN(F80, MAX($F$38-E80,0), $F$25*$F$38) -> 60.660463 | H80: =IFERROR(($F$42*E80 + $F$41*G80)/(E80+G80),0) -> 28.777134 | I80: =(E80+G80)*H80 -> 17619.146 | J80: =H80*(E80+G80)*$F$12 -> 880.95729 | K80: =C80*B25*B40*B80 -> 33096.092 | L80: =MIN(K80, $B$30*(1-$B$10)) -> 2546.04 | M80: =IFERROR(L80/$B$40,0) -> 2546.04 | N80: =M80*$B$15 -> 12730.2 | O80: =MAX($B$30*(1-$B$10)-L80,0) -> 0 | P80: =IFERROR(O80/$B$40,0) -> 0 | Q80: =P80*$B$16 -> 0 | R80: =I80+J80+N80+Q80 -> 31230.303
A81: M37 | B81: =INDEX($I$5:$I$16, 1+MOD(2-1,12)) -> 1.5 | C81: =MIN(C80*(1+$B$21), $B$22) -> 289.59081 | D81: =C81*$B$23*$B$24*$B$39*B81 -> 434.38621 | E81: =MIN(D81, $F$38) -> 434.38621 | F81: =(($B$31*$F$34*$B$10) + ($B$32*$F$35*$B$10))*(1+$F$24)*B81 -> 660.1518 | G81: =MIN(F81, MAX($F$38-E81,0), $F$25*$F$38) -> 177.87579 | H81: =IFERROR(($F$42*E81 + $F$41*G81)/(E81+G81),0) -> 30.55485 | I81: =(E81+G81)*H81 -> 18707.574 | J81: =H81*(E81+G81)*$F$12 -> 935.37869 | K81: =C81*$B$26*$B$40*B81 -> 5212.6345 | L81: =MIN(K81, $B$30*(1-$B$10)) -> 2546.04 | M81: =IFERROR(L81/$B$40,0) -> 2546.04 | N81: =M81*$B$15 -> 12730.2 | O81: =MAX($B$30*(1-$B$10)-L81,0) -> 0 | P81: =IFERROR(O81/$B$40,0) -> 0 | Q81: =P81*$B$16 -> 0 | R81: =I81+J81+N81+Q81 -> 32373.152
A82: M38 | B82: =INDEX($I$5:$I$16, 1+MOD(3-1,12)) -> 1.5 | C82: =MIN(C81*(1+$B$21), $B$22) -> 304.07035 | D82: =C82*$B$23*$B$24*$B$39*B82 -> 456.10552 | E82: =MIN(D82, $F$38) -> 456.10552 | F82: =(($B$31*$F$34*$B$10) + ($B$32*$F$35*$B$10))*(1+$F$24)*B82 -> 660.1518 | G82: =MIN(F82, MAX($F$38-E82,0), $F$25*$F$38) -> 156.15648 | H82: =IFERROR(($F$42*E82 + $F$41*G82)/(E82+G82),0) -> 30.22545 | I82: =(E82+G82)*H82 -> 18505.894 | J82: =H82*(E82+G82)*$F$12 -> 925.29472 | K82: =C82*B60*B75*B82 -> 437.8613 | L82: =MIN(K82, $B$30*(1-$B$10)) -> 437.8613 | M82: =IFERROR(L82/$B$40,0) -> 437.8613 | N82: =M82*$B$15 -> 2189.3065 | O82: =MAX($B$30*(1-$B$10)-L82,0) -> 2108.1787 | P82: =IFERROR(O82/$B$40,0) -> 2108.1787 | Q82: =P82*$B$16 -> 16865.43 | R82: =I82+J82+N82+Q82 -> 38485.925
A83: M39 | B83: =INDEX($I$5:$I$16, 1+MOD(4-1,12)) -> 1.2 | C83: =MIN(C82*(1+$B$21), $B$22) -> 319.27386 | D83: =C83*$B$23*$B$24*$B$39*B83 -> 383.12864 | E83: =MIN(D83, $F$38) -> 383.12864 | F83: =(($B$31*$F$34*$B$10) + ($B$32*$F$35*$B$10))*(1+$F$24)*B83 -> 528.12144 | G83: =MIN(F83, MAX($F$38-E83,0), $F$25*$F$38) -> 229.13336 | H83: =IFERROR(($F$42*E83 + $F$41*G83)/(E83+G83),0) -> 31.332235 | I83: =(E83+G83)*H83 -> 19183.537 | J83: =H83*(E83+G83)*$F$12 -> 959.17685 | K83: =C83*B60*B75*B83 -> 367.80349 | L83: =MIN(K83, $B$30*(1-$B$10)) -> 367.80349 | M83: =IFERROR(L83/$B$40,0) -> 367.80349 | N83: =M83*$B$15 -> 1839.0175 | O83: =MAX($B$30*(1-$B$10)-L83,0) -> 2178.2365 | P83: =IFERROR(O83/$B$40,0) -> 2178.2365 | Q83: =P83*$B$16 -> 17425.892 | R83: =I83+J83+N83+Q83 -> 39407.623
A84: M40 | B84: =INDEX($I$5:$I$16, 1+MOD(5-1,12)) -> 1 | C84: =MIN(C83*(1+$B$21), $B$22) -> 335.23756 | D84: =C84*$B$23*$B$24*$B$39*B84 -> 335.23756 | E84: =MIN(D84, $F$38) -> 335.23756 | F84: =(($B$31*$F$34*$B$10) + ($B$32*$F$35*$B$10))*(1+$F$24)*B84 -> 440.1012 | G84: =MIN(F84, MAX($F$38-E84,0), $F$25*$F$38) -> 277.02444 | H84: =IFERROR(($F$42*E84 + $F$41*G84)/(E84+G84),0) -> 32.058563 | I84: =(E84+G84)*H84 -> 19628.24 | J84: =H84*(E84+G84)*$F$12 -> 981.41199 | K84: =C84*B60*B75*B84 -> 321.82806 | L84: =MIN(K84, $B$30*(1-$B$10)) -> 321.82806 | M84: =IFERROR(L84/$B$40,0) -> 321.82806 | N84: =M84*$B$15 -> 1609.1403 | O84: =MAX($B$30*(1-$B$10)-L84,0) -> 2224.2119 | P84: =IFERROR(O84/$B$40,0) -> 2224.2119 | Q84: =P84*$B$16 -> 17793.696 | R84: =I84+J84+N84+Q84 -> 40012.488
A85: M41 | B85: =INDEX($I$5:$I$16, 1+MOD(6-1,12)) -> 0.8 | C85: =MIN(C84*(1+$B$21), $B$22) -> 351.99944 | D85: =C85*$B$23*$B$24*$B$39*B85 -> 281.59955 | E85: =MIN(D85, $F$38) -> 281.59955 | F85: =(($B$31*$F$34*$B$10) + ($B$32*$F$35*$B$10))*(1+$F$24)*B85 -> 352.08096 | G85: =MIN(F85, MAX($F$38-E85,0), $F$25*$F$38) -> 330.66245 | H85: =IFERROR(($F$42*E85 + $F$41*G85)/(E85+G85),0) -> 32.87205 | I85: =(E85+G85)*H85 -> 20126.307 | J85: =H85*(E85+G85)*$F$12 -> 1006.3154 | K85: =C85*B60*B75*B85 -> 270.33557 | L85: =MIN(K85, $B$30*(1-$B$10)) -> 270.33557 | M85: =IFERROR(L85/$B$40,0) -> 270.33557 | N85: =M85*$B$15 -> 1351.6778 | O85: =MAX($B$30*(1-$B$10)-L85,0) -> 2275.7044 | P85: =IFERROR(O85/$B$40,0) -> 2275.7044 | Q85: =P85*$B$16 -> 18205.635 | R85: =I85+J85+N85+Q85 -> 40689.936
A86: M42 | B86: =INDEX($I$5:$I$16, 1+MOD(7-1,12)) -> 0.8 | C86: =MIN(C85*(1+$B$21), $B$22) -> 369.59941 | D86: =C86*$B$23*$B$24*$B$39*B86 -> 295.67953 | E86: =MIN(D86, $F$38) -> 295.67953 | F86: =(($B$31*$F$34*$B$10) + ($B$32*$F$35*$B$10))*(1+$F$24)*B86 -> 352.08096 | G86: =MIN(F86, MAX($F$38-E86,0), $F$25*$F$38) -> 316.58247 | H86: =IFERROR(($F$42*E86 + $F$41*G86)/(E86+G86),0) -> 32.65851 | I86: =(E86+G86)*H86 -> 19995.564 | J86: =H86*(E86+G86)*$F$12 -> 999.77822 | K86: =C86*B60*B75*B86 -> 283.85234 | L86: =MIN(K86, $B$30*(1-$B$10)) -> 283.85234 | M86: =IFERROR(L86/$B$40,0) -> 283.85234 | N86: =M86*$B$15 -> 1419.2617 | O86: =MAX($B$30*(1-$B$10)-L86,0) -> 2262.1877 | P86: =IFERROR(O86/$B$40,0) -> 2262.1877 | Q86: =P86*$B$16 -> 18097.501 | R86: =I86+J86+N86+Q86 -> 40512.106
A87: M43 | B87: =INDEX($I$5:$I$16, 1+MOD(8-1,12)) -> 0.8 | C87: =MIN(C86*(1+$B$21), $B$22) -> 388.07938 | D87: =C87*$B$23*$B$24*$B$39*B87 -> 310.4635 | E87: =MIN(D87, $F$38) -> 310.4635 | F87: =(($B$31*$F$34*$B$10) + ($B$32*$F$35*$B$10))*(1+$F$24)*B87 -> 352.08096 | G87: =MIN(F87, MAX($F$38-E87,0), $F$25*$F$38) -> 301.7985 | H87: =IFERROR(($F$42*E87 + $F$41*G87)/(E87+G87),0) -> 32.434292 | I87: =(E87+G87)*H87 -> 19858.285 | J87: =H87*(E87+G87)*$F$12 -> 992.91423 | K87: =C87*B60*B75*B87 -> 298.04496 | L87: =MIN(K87, $B$30*(1-$B$10)) -> 298.04496 | M87: =IFERROR(L87/$B$40,0) -> 298.04496 | N87: =M87*$B$15 -> 1490.2248 | O87: =MAX($B$30*(1-$B$10)-L87,0) -> 2247.995 | P87: =IFERROR(O87/$B$40,0) -> 2247.995 | Q87: =P87*$B$16 -> 17983.96 | R87: =I87+J87+N87+Q87 -> 40325.384
A88: M44 | B88: =INDEX($I$5:$I$16, 1+MOD(9-1,12)) -> 1 | C88: =MIN(C87*(1+$B$21), $B$22) -> 407.48335 | D88: =C88*$B$23*$B$24*$B$39*B88 -> 407.48335 | E88: =MIN(D88, $F$38) -> 407.48335 | F88: =(($B$31*$F$34*$B$10) + ($B$32*$F$35*$B$10))*(1+$F$24)*B88 -> 440.1012 | G88: =MIN(F88, MAX($F$38-E88,0), $F$25*$F$38) -> 204.77865 | H88: =IFERROR(($F$42*E88 + $F$41*G88)/(E88+G88),0) -> 30.962866 | I88: =(E88+G88)*H88 -> 18957.386 | J88: =H88*(E88+G88)*$F$12 -> 947.8693 | K88: =C88*B60*B75*B88 -> 391.18401 | L88: =MIN(K88, $B$30*(1-$B$10)) -> 391.18401 | M88: =IFERROR(L88/$B$40,0) -> 391.18401 | N88: =M88*$B$15 -> 1955.9201 | O88: =MAX($B$30*(1-$B$10)-L88,0) -> 2154.856 | P88: =IFERROR(O88/$B$40,0) -> 2154.856 | Q88: =P88*$B$16 -> 17238.848 | R88: =I88+J88+N88+Q88 -> 39100.023
A89: M45 | B89: =INDEX($I$5:$I$16, 1+MOD(10-1,12)) -> 1.2 | C89: =MIN(C88*(1+$B$21), $B$22) -> 427.85751 | D89: =C89*$B$23*$B$24*$B$39*B89 -> 513.42902 | E89: =MIN(D89, $F$38) -> 513.42902 | F89: =(($B$31*$F$34*$B$10) + ($B$32*$F$35*$B$10))*(1+$F$24)*B89 -> 528.12144 | G89: =MIN(F89, MAX($F$38-E89,0), $F$25*$F$38) -> 98.832983 | H89: =IFERROR(($F$42*E89 + $F$41*G89)/(E89+G89),0) -> 29.356068 | I89: =(E89+G89)*H89 -> 17973.605 | J89: =H89*(E89+G89)*$F$12 -> 898.68024 | K89: =C89*B60*B75*B89 -> 492.89186 | L89: =MIN(K89, $B$30*(1-$B$10)) -> 492.89186 | M89: =IFERROR(L89/$B$40,0) -> 492.89186 | N89: =M89*$B$15 -> 2464.4593 | O89: =MAX($B$30*(1-$B$10)-L89,0) -> 2053.1481 | P89: =IFERROR(O89/$B$40,0) -> 2053.1481 | Q89: =P89*$B$16 -> 16425.185 | R89: =I89+J89+N89+Q89 -> 37761.93
A90: M46 | B90: =INDEX($I$5:$I$16, 1+MOD(11-1,12)) -> 1.5 | C90: =MIN(C89*(1+$B$21), $B$22) -> 449.25039 | D90: =C90*$B$23*$B$24*$B$39*B90 -> 673.87558 | E90: =MIN(D90, $F$38) -> 612.262 | F90: =(($B$31*$F$34*$B$10) + ($B$32*$F$35*$B$10))*(1+$F$24)*B90 -> 660.1518 | G90: =MIN(F90, MAX($F$38-E90,0), $F$25*$F$38) -> 0 | H90: =IFERROR(($F$42*E90 + $F$41*G90)/(E90+G90),0) -> 27.857143 | I90: =(E90+G90)*H90 -> 17055.87 | J90: =H90*(E90+G90)*$F$12 -> 852.7935 | K90: =C90*B60*B75*B90 -> 646.92056 | L90: =MIN(K90, $B$30*(1-$B$10)) -> 646.92056 | M90: =IFERROR(L90/$B$40,0) -> 646.92056 | N90: =M90*$B$15 -> 3234.6028 | O90: =MAX($B$30*(1-$B$10)-L90,0) -> 1899.1194 | P90: =IFERROR(O90/$B$40,0) -> 1899.1194 | Q90: =P90*$B$16 -> 15192.956 | R90: =I90+J90+N90+Q90 -> 36336.222
A91: M47 | B91: =INDEX($I$5:$I$16, 1+MOD(12-1,12)) -> 2 | C91: =MIN(C90*(1+$B$21), $B$22) -> 471.71291 | D91: =C91*$B$23*$B$24*$B$39*B91 -> 943.42582 | E91: =MIN(D91, $F$38) -> 612.262 | F91: =(($B$31*$F$34*$B$10) + ($B$32*$F$35*$B$10))*(1+$F$24)*B91 -> 880.2024 | G91: =MIN(F91, MAX($F$38-E91,0), $F$25*$F$38) -> 0 | H91: =IFERROR(($F$42*E91 + $F$41*G91)/(E91+G91),0) -> 27.857143 | I91: =(E91+G91)*H91 -> 17055.87 | J91: =H91*(E91+G91)*$F$12 -> 852.7935 | K91: =C91*B60*B75*B91 -> 905.68879 | L91: =MIN(K91, $B$30*(1-$B$10)) -> 905.68879 | M91: =IFERROR(L91/$B$40,0) -> 905.68879 | N91: =M91*$B$15 -> 4528.4439 | O91: =MAX($B$30*(1-$B$10)-L91,0) -> 1640.3512 | P91: =IFERROR(O91/$B$40,0) -> 1640.3512 | Q91: =P91*$B$16 -> 13122.81 | R91: =I91+J91+N91+Q91 -> 35559.917
A92: M48 | B92: =INDEX($I$5:$I$16, 1+MOD(13-1,12)) -> 2 | C92: =MIN(C91*(1+$B$21), $B$22) -> 495.29855 | D92: =C92*$B$23*$B$24*$B$39*B92 -> 990.59711 | E92: =MIN(D92, $F$38) -> 612.262 | F92: =(($B$31*$F$34*$B$10) + ($B$32*$F$35*$B$10))*(1+$F$24)*B92 -> 880.2024 | G92: =MIN(F92, MAX($F$38-E92,0), $F$25*$F$38) -> 0 | H92: =IFERROR(($F$42*E92 + $F$41*G92)/(E92+G92),0) -> 27.857143 | I92: =(E92+G92)*H92 -> 17055.87 | J92: =H92*(E92+G92)*$F$12 -> 852.7935 | K92: =C92*B60*B75*B92 -> 950.97322 | L92: =MIN(K92, $B$30*(1-$B$10)) -> 950.97322 | M92: =IFERROR(L92/$B$40,0) -> 950.97322 | N92: =M92*$B$15 -> 4754.8661 | O92: =MAX($B$30*(1-$B$10)-L92,0) -> 1595.0668 | P92: =IFERROR(O92/$B$40,0) -> 1595.0668 | Q92: =P92*$B$16 -> 12760.534 | R92: =I92+J92+N92+Q92 -> 35424.064
A94: Quarterly Summary
A95: Quarter | B95: Members (avg) | C95: Reservation Revenue (incl. no-shows) | D95: Open Play Revenue | E95: TOTAL Court Revenue
A96: Q1 (M1–M3) | B96: =AVERAGE('Court Revenue (36m)'!C45:'Court Revenue (36m)'!C47) -> 52.541667 | C96: =SUM('Court Revenue (36m)'!I45:I47)+SUM('Court Revenue (36m)'!J45:J47) -> 69085.638 | D96: =SUM('Court Revenue (36m)'!N45:N47)+SUM('Court Revenue (36m)'!Q45:Q47) -> 47031.84 | E96: =SUM('Court Revenue (36m)'!R45:R47) -> 116117.48
A97: Q2 (M4–M6) | B97: =AVERAGE('Court Revenue (36m)'!C48:'Court Revenue (36m)'!C50) -> 60.823547 | C97: =SUM('Court Revenue (36m)'!I48:I50)+SUM('Court Revenue (36m)'!J48:J50) -> 56794.4 | D97: =SUM('Court Revenue (36m)'!N48:N50)+SUM('Court Revenue (36m)'!Q48:Q50) -> 38190.6 | E97: =SUM('Court Revenue (36m)'!R48:R50) -> 94985
A98: Q3 (M7–M9) | B98: =AVERAGE('Court Revenue (36m)'!C51:'Court Revenue (36m)'!C53) -> 70.410858 | C98: =SUM('Court Revenue (36m)'!I51:I53)+SUM('Court Revenue (36m)'!J51:J53) -> 50001.26 | D98: =SUM('Court Revenue (36m)'!N51:N53)+SUM('Court Revenue (36m)'!Q51:Q53) -> 38190.6 | E98: =SUM('Court Revenue (36m)'!R51:R53) -> 88191.86
A99: Q4 (M10–M12) | B99: =AVERAGE('Court Revenue (36m)'!C54:'Court Revenue (36m)'!C56) -> 81.50937 | C99: =SUM('Court Revenue (36m)'!I54:I56)+SUM('Court Revenue (36m)'!J54:J56) -> 67868.417 | D99: =SUM('Court Revenue (36m)'!N54:N56)+SUM('Court Revenue (36m)'!Q54:Q56) -> 38190.6 | E99: =SUM('Court Revenue (36m)'!R54:R56) -> 106059.02
A100: Q5 (M13–M15) | B100: =AVERAGE('Court Revenue (36m)'!C57:'Court Revenue (36m)'!C59) -> 94.357284 | C100: =SUM('Court Revenue (36m)'!I57:I59)+SUM('Court Revenue (36m)'!J57:J59) -> 67056.988 | D100: =SUM('Court Revenue (36m)'!N57:N59)+SUM('Court Revenue (36m)'!Q57:Q59) -> 38190.6 | E100: =SUM('Court Revenue (36m)'!R57:R59) -> 105247.59
A101: Q6 (M16–M18) | B101: =AVERAGE('Court Revenue (36m)'!C60:'Court Revenue (36m)'!C62) -> 109.23035 | C101: =SUM('Court Revenue (36m)'!I60:I62)+SUM('Court Revenue (36m)'!J60:J62) -> 59431.265 | D101: =SUM('Court Revenue (36m)'!N60:N62)+SUM('Court Revenue (36m)'!Q60:Q62) -> 38190.6 | E101: =SUM('Court Revenue (36m)'!R60:R62) -> 97621.865
A102: Q7 (M19–M21) | B102: =AVERAGE('Court Revenue (36m)'!C63:'Court Revenue (36m)'!C65) -> 126.44779 | C102: =SUM('Court Revenue (36m)'!I63:I65)+SUM('Court Revenue (36m)'!J63:J65) -> 54278.986 | D102: =SUM('Court Revenue (36m)'!N63:N65)+SUM('Court Revenue (36m)'!Q63:Q65) -> 38190.6 | E102: =SUM('Court Revenue (36m)'!R63:R65) -> 92469.586
A103: Q8 (M22–M24) | B103: =AVERAGE('Court Revenue (36m)'!C66:'Court Revenue (36m)'!C68) -> 146.37912 | C103: =SUM('Court Revenue (36m)'!I66:I68)+SUM('Court Revenue (36m)'!J66:J68) -> 64871.033 | D103: =SUM('Court Revenue (36m)'!N66:N68)+SUM('Court Revenue (36m)'!Q66:Q68) -> 38190.6 | E103: =SUM('Court Revenue (36m)'!R66:R68) -> 103061.63
A104: Q9 (M25–M27) | B104: =AVERAGE('Court Revenue (36m)'!C69:'Court Revenue (36m)'!C71) -> 169.45213 | C104: =SUM('Court Revenue (36m)'!I69:I71)+SUM('Court Revenue (36m)'!J69:J71) -> 63413.824 | D104: =SUM('Court Revenue (36m)'!N69:N71)+SUM('Court Revenue (36m)'!Q69:Q71) -> 38190.6 | E104: =SUM('Court Revenue (36m)'!R69:R71) -> 101604.42
A105: Q10 (M28–M30) | B105: =AVERAGE('Court Revenue (36m)'!C72:'Court Revenue (36m)'!C74) -> 196.16202 | C105: =SUM('Court Revenue (36m)'!I72:I74)+SUM('Court Revenue (36m)'!J72:J74) -> 62208.337 | D105: =SUM('Court Revenue (36m)'!N72:N74)+SUM('Court Revenue (36m)'!Q72:Q74) -> 38190.6 | E105: =SUM('Court Revenue (36m)'!R72:R74) -> 100398.94
A106: Q11 (M31–M33) | B106: =AVERAGE('Court Revenue (36m)'!C75:'Court Revenue (36m)'!C77) -> 227.08206 | C106: =SUM('Court Revenue (36m)'!I75:I77)+SUM('Court Revenue (36m)'!J75:J77) -> 59383.803 | D106: =SUM('Court Revenue (36m)'!N75:N77)+SUM('Court Revenue (36m)'!Q75:Q77) -> 38190.6 | E106: =SUM('Court Revenue (36m)'!R75:R77) -> 97574.403
...

Sheet Revenue Model
A1: Monthly Revenue Model (first 36 months)
A2: Uses court utilization + pricing + memberships + lessons + leagues + retail/cafe.
A4: Month | B4: Court Revenue | C4: Members | D4: Memberships | E4: Lessons | F4: Leagues | G4: Retail | H4: Cafe | I4: Total Revenue
A5: 1 | B5: ='Court Revenue (36m)'!R45 -> 39671.538 | C5: =Assumptions!B16 -> 50 | D5: =C5*Assumptions!$B$17 -> 4602.5 | E5: =Assumptions!$B$19*4.33*Assumptions!$B$20 -> 6754.8 | F5: =(Assumptions!$B$21*Assumptions!$B$22*Assumptions!$B$23)/12 -> 1000 | G5: =Assumptions!$B$24 -> 3000 | H5: =Assumptions!$B$26 -> 5000 | I5: =SUM(B5:H5) -> 60078.838
A6: 2 | B6: ='Court Revenue (36m)'!R46 -> 40643.726 | C6: =(1+Assumptions!$B$18)*C5 -> 52.5 | D6: =C6*Assumptions!$B$17 -> 4832.625 | E6: =Assumptions!$B$19*4.33*Assumptions!$B$20 -> 6754.8 | F6: =(Assumptions!$B$21*Assumptions!$B$22*Assumptions!$B$23)/12 -> 1000 | G6: =Assumptions!$B$24 -> 3000 | H6: =Assumptions!$B$26 -> 5000 | I6: =SUM(B6:H6) -> 61283.651
A7: 3 | B7: ='Court Revenue (36m)'!R47 -> 35802.215 | C7: =(1+Assumptions!$B$18)*C6 -> 55.125 | D7: =C7*Assumptions!$B$17 -> 5074.2562 | E7: =Assumptions!$B$19*4.33*Assumptions!$B$20 -> 6754.8 | F7: =(Assumptions!$B$21*Assumptions!$B$22*Assumptions!$B$23)/12 -> 1000 | G7: =Assumptions!$B$24 -> 3000 | H7: =Assumptions!$B$26 -> 5000 | I7: =SUM(B7:H7) -> 56686.396
A8: 4 | B8: ='Court Revenue (36m)'!R48 -> 35358.568 | C8: =(1+Assumptions!$B$18)*C7 -> 57.88125 | D8: =C8*Assumptions!$B$17 -> 5327.9691 | E8: =Assumptions!$B$19*4.33*Assumptions!$B$20 -> 6754.8 | F8: =(Assumptions!$B$21*Assumptions!$B$22*Assumptions!$B$23)/12 -> 1000 | G8: =Assumptions!$B$24 -> 3000 | H8: =Assumptions!$B$26 -> 5000 | I8: =SUM(B8:H8) -> 56499.218
A9: 5 | B9: ='Court Revenue (36m)'!R49 -> 31671.825 | C9: =(1+Assumptions!$B$18)*C8 -> 60.775313 | D9: =C9*Assumptions!$B$17 -> 5594.3675 | E9: =Assumptions!$B$19*4.33*Assumptions!$B$20 -> 6754.8 | F9: =(Assumptions!$B$21*Assumptions!$B$22*Assumptions!$B$23)/12 -> 1000 | G9: =Assumptions!$B$24 -> 3000 | H9: =Assumptions!$B$26 -> 5000 | I9: =SUM(B9:H9) -> 53081.768
A10: 6 | B10: ='Court Revenue (36m)'!R50 -> 27954.607 | C10: =(1+Assumptions!$B$18)*C9 -> 63.814078 | D10: =C10*Assumptions!$B$17 -> 5874.0859 | E10: =Assumptions!$B$19*4.33*Assumptions!$B$20 -> 6754.8 | F10: =(Assumptions!$B$21*Assumptions!$B$22*Assumptions!$B$23)/12 -> 1000 | G10: =Assumptions!$B$24 -> 3000 | H10: =Assumptions!$B$26 -> 5000 | I10: =SUM(B10:H10) -> 49647.307
A11: 7 | B11: ='Court Revenue (36m)'!R51 -> 28029.269 | C11: =(1+Assumptions!$B$18)*C10 -> 67.004782 | D11: =C11*Assumptions!$B$17 -> 6167.7902 | E11: =Assumptions!$B$19*4.33*Assumptions!$B$20 -> 6754.8 | F11: =(Assumptions!$B$21*Assumptions!$B$22*Assumptions!$B$23)/12 -> 1000 | G11: =Assumptions!$B$24 -> 3000 | H11: =Assumptions!$B$26 -> 5000 | I11: =SUM(B11:H11) -> 50018.864
A12: 8 | B12: ='Court Revenue (36m)'!R52 -> 28107.665 | C12: =(1+Assumptions!$B$18)*C11 -> 70.355021 | D12: =C12*Assumptions!$B$17 -> 6476.1797 | E12: =Assumptions!$B$19*4.33*Assumptions!$B$20 -> 6754.8 | F12: =(Assumptions!$B$21*Assumptions!$B$22*Assumptions!$B$23)/12 -> 1000 | G12: =Assumptions!$B$24 -> 3000 | H12: =Assumptions!$B$26 -> 5000 | I12: =SUM(B12:H12) -> 50409
A13: 9 | B13: ='Court Revenue (36m)'!R53 -> 32054.925 | C13: =(1+Assumptions!$B$18)*C12 -> 73.872772 | D13: =C13*Assumptions!$B$17 -> 6799.9887 | E13: =Assumptions!$B$19*4.33*Assumptions!$B$20 -> 6754.8 | F13: =(Assumptions!$B$21*Assumptions!$B$22*Assumptions!$B$23)/12 -> 1000 | G13: =Assumptions!$B$24 -> 3000 | H13: =Assumptions!$B$26 -> 5000 | I13: =SUM(B13:H13) -> 54683.587
A14: 10 | B14: ='Court Revenue (36m)'!R54 -> 35700.891 | C14: =(1+Assumptions!$B$18)*C13 -> 77.566411 | D14: =C14*Assumptions!$B$17 -> 7139.9881 | E14: =Assumptions!$B$19*4.33*Assumptions!$B$20 -> 6754.8 | F14: =(Assumptions!$B$21*Assumptions!$B$22*Assumptions!$B$23)/12 -> 1000 | G14: =Assumptions!$B$24 -> 3000 | H14: =Assumptions!$B$26 -> 5000 | I14: =SUM(B14:H14) -> 58673.246
A15: 11 | B15: ='Court Revenue (36m)'!R55 -> 35417.289 | C15: =(1+Assumptions!$B$18)*C14 -> 81.444731 | D15: =C15*Assumptions!$B$17 -> 7496.9875 | E15: =Assumptions!$B$19*4.33*Assumptions!$B$20 -> 6754.8 | F15: =(Assumptions!$B$21*Assumptions!$B$22*Assumptions!$B$23)/12 -> 1000 | G15: =Assumptions!$B$24 -> 3000 | H15: =Assumptions!$B$26 -> 5000 | I15: =SUM(B15:H15) -> 58750.521
A16: 12 | B16: ='Court Revenue (36m)'!R56 -> 34940.837 | C16: =(1+Assumptions!$B$18)*C15 -> 85.516968 | D16: =C16*Assumptions!$B$17 -> 7871.8369 | E16: =Assumptions!$B$19*4.33*Assumptions!$B$20 -> 6754.8 | F16: =(Assumptions!$B$21*Assumptions!$B$22*Assumptions!$B$23)/12 -> 1000 | G16: =Assumptions!$B$24 -> 3000 | H16: =Assumptions!$B$26 -> 5000 | I16: =SUM(B16:H16) -> 58652.991
A17: 13 | B17: ='Court Revenue (36m)'!R57 -> 34857.458 | C17: =(1+Assumptions!$B$18)*C16 -> 89.792816 | D17: =C17*Assumptions!$B$17 -> 8265.4287 | E17: =Assumptions!$B$19*4.33*Assumptions!$B$20 -> 6754.8 | F17: =(Assumptions!$B$21*Assumptions!$B$22*Assumptions!$B$23)/12 -> 1000 | G17: =Assumptions!$B$24 -> 3000 | H17: =Assumptions!$B$26 -> 5000 | I17: =SUM(B17:H17) -> 58967.48
... A52: 48 | B52: ='Court Revenue (36m)'!R92 -> 35424.064 | C52: =(1+Assumptions!$B$18)*C51 -> 495.29855 | D52: =C52*Assumptions!$B$17 -> 45592.232 | E52: =Assumptions!$B$19*4.33*Assumptions!$B$20 -> 6754.8 | F52: =(Assumptions!$B$21*Assumptions!$B$22*Assumptions!$B$23)/12 -> 1000 | G52: =Assumptions!$B$24 -> 3000 | H52: =Assumptions!$B$26 -> 5000 | I52: =SUM(B52:H52) -> 97266.394

Sheet Staffing & Payroll
A1: Weekly Staffing Plan (links to Assumptions)
A3: Role | B3: Hours/Week | C3: Wage $/hr | D3: Weekly Payroll | E3: Monthly Payroll (≈4.33x)
A4: Front Desk | B4: =Assumptions!B28 -> 196 | C4: =Assumptions!B29 -> 18 | D4: =B4*C4 -> 3528 | E4: =D4*4.33 -> 15276.24
A5: Coaches | B5: =Assumptions!B30 -> 40 | C5: =Assumptions!B31 -> 30 | D5: =B5*C5 -> 1200 | E5: =D5*4.33 -> 5196
A6: Cafe | B6: =Assumptions!B32 -> 60 | C6: =Assumptions!B33 -> 17 | D6: =B6*C6 -> 1020 | E6: =D6*4.33 -> 4416.6
A7: Totals | D7: =SUM(D4:D6) -> 5748 | E7: =SUM(E4:E6) -> 24888.84

Sheet OPEX
A1: Operating Expenses (Monthly)
A2: Expected OPEX
A3: Category | B3: Amount ($/mo) | D3: COGS Helpers
A4: Base Rent | B4: 30000 | D4: Retail COGS $/mo | E4: =Assumptions!B24*Assumptions!B25 -> 1650
A5: Utilities | B5: =Assumptions!B35 -> 6000 | D5: Cafe COGS $/mo | E5: =Assumptions!B26*Assumptions!B27 -> 2250
A6: Insurance | B6: 2000 | D6: Total COGS $/mo | E6: =E4+E5 -> 3900
A7: Marketing | B7: =Assumptions!B37 -> 4000
A8: Software | B8: =Assumptions!B38 -> 2000
A9: Cleaning & Supplies | B9: 2200
A10: Misc. Opex | B10: =Assumptions!B40 -> 2000
A11: Total OPEX (incl. rent) | B11: =SUM(B4:B10) -> 48200

Sheet P&L (36m)
A1: Profit & Loss – Monthly (36 months)
A2: Predicted P&L
A3: Month | B3: Total Revenue | C3: COGS | D3: Payroll | E3: OPEX | F3: EBITDA | G3: Interest | H3: EBT
A4: 1 | B4: ='Revenue Model'!I5 -> 60078.838 | C4: =OPEX!E6 -> 3900 | D4: ='Staffing & Payroll'!E7 -> 24888.84 | E4: =OPEX!B11 -> 48200 | F4: =B4-C4-D4-E4 -> -16910.002 | G4: =Financing!D4 -> 15833.333 | H4: =F4-G4 -> -32743.335
A5: 2 | B5: ='Revenue Model'!I6 -> 61283.651 | C5: =OPEX!E6 -> 3900 | D5: ='Staffing & Payroll'!E7 -> 24888.84 | E5: =OPEX!B11 -> 48200 | F5: =B5-C5-D5-E5 -> -15705.189 | G5: =Financing!D5 -> 15753.801 | H5: =F4-G4 -> -32743.335
A6: 3 | B6: ='Revenue Model'!I7 -> 56686.396 | C6: =OPEX!E6 -> 3900 | D6: ='Staffing & Payroll'!E7 -> 24888.84 | E6: =OPEX!B11 -> 48200 | F6: =B6-C6-D6-E6 -> -20302.444 | G6: =Financing!D6 -> 15673.639 | H6: =F5-G5 -> -31458.991
A7: 4 | B7: ='Revenue Model'!I8 -> 56499.218 | C7: =OPEX!E6 -> 3900 | D7: ='Staffing & Payroll'!E7 -> 24888.84 | E7: =OPEX!B11 -> 48200 | F7: =B7-C7-D7-E7 -> -20489.622 | G7: =Financing!D7 -> 15592.843 | H7: =F6-G6 -> -35976.083
A8: 5 | B8: ='Revenue Model'!I9 -> 53081.768 | C8: =OPEX!E6 -> 3900 | D8: ='Staffing & Payroll'!E7 -> 24888.84 | E8: =OPEX!B11 -> 48200 | F8: =B8-C8-D8-E8 -> -23907.072 | G8: =Financing!D8 -> 15511.407 | H8: =F7-G7 -> -36082.464
A9: 6 | B9: ='Revenue Model'!I10 -> 49647.307 | C9: =OPEX!E6 -> 3900 | D9: ='Staffing & Payroll'!E7 -> 24888.84 | E9: =OPEX!B11 -> 48200 | F9: =B9-C9-D9-E9 -> -27341.533 | G9: =Financing!D9 -> 15429.326 | H9: =F8-G8 -> -39418.479
A10: 7 | B10: ='Revenue Model'!I11 -> 50018.864 | C10: =OPEX!E6 -> 3900 | D10: ='Staffing & Payroll'!E7 -> 24888.84 | E10: =OPEX!B11 -> 48200 | F10: =B10-C10-D10-E10 -> -26969.976 | G10: =Financing!D10 -> 15346.595 | H10: =F9-G9 -> -42770.859
A11: 8 | B11: ='Revenue Model'!I12 -> 50409 | C11: =OPEX!E6 -> 3900 | D11: ='Staffing & Payroll'!E7 -> 24888.84 | E11: =OPEX!B11 -> 48200 | F11: =B11-C11-D11-E11 -> -26579.84 | G11: =Financing!D11 -> 15263.21 | H11: =F10-G10 -> -42316.571
A12: 9 | B12: ='Revenue Model'!I13 -> 54683.587 | C12: =OPEX!E6 -> 3900 | D12: ='Staffing & Payroll'!E7 -> 24888.84 | E12: =OPEX!B11 -> 48200 | F12: =B12-C12-D12-E12 -> -22305.253 | G12: =Financing!D12 -> 15179.164 | H12: =F11-G11 -> -41843.05
A13: 10 | B13: ='Revenue Model'!I14 -> 58673.246 | C13: =OPEX!E6 -> 3900 | D13: ='Staffing & Payroll'!E7 -> 24888.84 | E13: =OPEX!B11 -> 48200 | F13: =B13-C13-D13-E13 -> -18315.594 | G13: =Financing!D13 -> 15094.453 | H13: =F12-G12 -> -37484.417
A14: 11 | B14: ='Revenue Model'!I15 -> 58750.521 | C14: =OPEX!E6 -> 3900 | D14: ='Staffing & Payroll'!E7 -> 24888.84 | E14: =OPEX!B11 -> 48200 | F14: =B14-C14-D14-E14 -> -18238.319 | G14: =Financing!D14 -> 15009.071 | H14: =F13-G13 -> -33410.047
A15: 12 | B15: ='Revenue Model'!I16 -> 58652.991 | C15: =OPEX!E6 -> 3900 | D15: ='Staffing & Payroll'!E7 -> 24888.84 | E15: =OPEX!B11 -> 48200 | F15: =B15-C15-D15-E15 -> -18335.849 | G15: =Financing!D15 -> 14923.013 | H15: =F14-G14 -> -33247.39
A16: 13 | B16: ='Revenue Model'!I17 -> 58967.48 | C16: =OPEX!E6 -> 3900 | D16: ='Staffing & Payroll'!E7 -> 24888.84 | E16: =OPEX!B11 -> 48200 | F16: =B16-C16-D16-E16 -> -18021.36 | G16: =Financing!D16 -> 14836.274 | H16: =F15-G15 -> -33258.862
A17: 14 | B17: ='Revenue Model'!I18 -> 59757.32 | C17: =OPEX!E6 -> 3900 | D17: ='Staffing & Payroll'!E7 -> 24888.84 | E17: =OPEX!B11 -> 48200 | F17: =B17-C17-D17-E17 -> -17231.52 | G17: =Financing!D17 -> 14748.849 | H17: =F16-G16 -> -32857.635
A18: 15 | B18: ='Revenue Model'!I19 -> 60127.025 | C18: =OPEX!E6 -> 3900 | D18: ='Staffing & Payroll'!E7 -> 24888.84 | E18: =OPEX!B11 -> 48200 | F18: =B18-C18-D18-E18 -> -16861.815 | G18: =Financing!D18 -> 14660.731 | H18: =F17-G17 -> -31980.369
A19: 16 | B19: ='Revenue Model'!I20 -> 60819.258 | C19: =OPEX!E6 -> 3900 | D19: ='Staffing & Payroll'!E7 -> 24888.84 | E19: =OPEX!B11 -> 48200 | F19: =B19-C19-D19-E19 -> -16169.582 | G19: =Financing!D19 -> 14571.916 | H19: =F18-G18 -> -31522.546
A20: 17 | B20: ='Revenue Model'!I21 -> 58997.225 | C20: =OPEX!E6 -> 3900 | D20: ='Staffing & Payroll'!E7 -> 24888.84 | E20: =OPEX!B11 -> 48200 | F20: =B20-C20-D20-E20 -> -17991.615 | G20: =Financing!D20 -> 14482.397 | H20: =F19-G19 -> -30741.497
A21: 18 | B21: ='Revenue Model'!I22 -> 55561.434 | C21: =OPEX!E6 -> 3900 | D21: ='Staffing & Payroll'!E7 -> 24888.84 | E21: =OPEX!B11 -> 48200 | F21: =B21-C21-D21-E21 -> -21427.406 | G21: =Financing!D21 -> 14392.17 | H21: =F20-G20 -> -32474.012
A22: 19 | B22: ='Revenue Model'!I23 -> 56228.698 | C22: =OPEX!E6 -> 3900 | D22: ='Staffing & Payroll'!E7 -> 24888.84 | E22: =OPEX!B11 -> 48200 | F22: =B22-C22-D22-E22 -> -20760.142 | G22: =Financing!D22 -> 14301.229 | H22: =F21-G21 -> -35819.576
A23: 20 | B23: ='Revenue Model'!I24 -> 56929.325 | C23: =OPEX!E6 -> 3900 | D23: ='Staffing & Payroll'!E7 -> 24888.84 | E23: =OPEX!B11 -> 48200 | F23: =B23-C23-D23-E23 -> -20059.515 | G23: =Financing!D23 -> 14209.567 | H23: =F22-G22 -> -35061.371
A24: 21 | B24: ='Revenue Model'!I25 -> 61873.862 | C24: =OPEX!E6 -> 3900 | D24: ='Staffing & Payroll'!E7 -> 24888.84 | E24: =OPEX!B11 -> 48200 | F24: =B24-C24-D24-E24 -> -15114.978 | G24: =Financing!D24 -> 14117.18 | H24: =F23-G23 -> -34269.082
A25: 22 | B25: ='Revenue Model'!I26 -> 63695.121 | C25: =OPEX!E6 -> 3900 | D25: ='Staffing & Payroll'!E7 -> 24888.84 | E25: =OPEX!B11 -> 48200 | F25: =B25-C25-D25-E25 -> -13293.719 | G25: =Financing!D25 -> 14024.062 | H25: =F24-G24 -> -29232.158
A26: 23 | B26: ='Revenue Model'!I27 -> 63833.897 | C26: =OPEX!E6 -> 3900 | D26: ='Staffing & Payroll'!E7 -> 24888.84 | E26: =OPEX!B11 -> 48200 | F26: =B26-C26-D26-E26 -> -13154.943 | G26: =Financing!D26 -> 13930.206 | H26: =F25-G25 -> -27317.781
A27: 24 | B27: ='Revenue Model'!I28 -> 63658.747 | C27: =OPEX!E6 -> 3900 | D27: ='Staffing & Payroll'!E7 -> 24888.84 | E27: =OPEX!B11 -> 48200 | F27: =B27-C27-D27-E27 -> -13330.093 | G27: =Financing!D27 -> 13835.607 | H27: =F26-G26 -> -27085.149
A28: 25 | B28: ='Revenue Model'!I29 -> 64223.523 | C28: =OPEX!E6 -> 3900 | D28: ='Staffing & Payroll'!E7 -> 24888.84 | E28: =OPEX!B11 -> 48200 | F28: =B28-C28-D28-E28 -> -12765.317 | G28: =Financing!D28 -> 13740.26 | H28: =F27-G27 -> -27165.701
A29: 26 | B29: ='Revenue Model'!I30 -> 65641.962 | C29: =OPEX!E6 -> 3900 | D29: ='Staffing & Payroll'!E7 -> 24888.84 | E29: =OPEX!B11 -> 48200 | F29: =B29-C29-D29-E29 -> -11346.878 | G29: =Financing!D29 -> 13644.157 | H29: =F28-G28 -> -26505.577
A30: 27 | B30: ='Revenue Model'!I31 -> 66305.9 | C30: =OPEX!E6 -> 3900 | D30: ='Staffing & Payroll'!E7 -> 24888.84 | E30: =OPEX!B11 -> 48200 | F30: =B30-C30-D30-E30 -> -10682.94 | G30: =Financing!D30 -> 13547.294 | H30: =F29-G29 -> -24991.035
A31: 28 | B31: ='Revenue Model'!I32 -> 67549.052 | C31: =OPEX!E6 -> 3900 | D31: ='Staffing & Payroll'!E7 -> 24888.84 | E31: =OPEX!B11 -> 48200 | F31: =B31-C31-D31-E31 -> -9439.7884 | G31: =Financing!D31 -> 13449.664 | H31: =F30-G30 -> -24230.235
A32: 29 | B32: ='Revenue Model'!I33 -> 68690.556 | C32: =OPEX!E6 -> 3900 | D32: ='Staffing & Payroll'!E7 -> 24888.84 | E32: =OPEX!B11 -> 48200 | F32: =B32-C32-D32-E32 -> -8298.2841 | G32: =Financing!D32 -> 13351.261 | H32: =F31-G31 -> -22889.453
A33: 30 | B33: ='Revenue Model'!I34 -> 66182.357 | C33: =OPEX!E6 -> 3900 | D33: ='Staffing & Payroll'!E7 -> 24888.84 | E33: =OPEX!B11 -> 48200 | F33: =B33-C33-D33-E33 -> -10806.483 | G33: =Financing!D33 -> 13252.079 | H33: =F32-G32 -> -21649.545
A34: 31 | B34: ='Revenue Model'!I35 -> 67380.667 | C34: =OPEX!E6 -> 3900 | D34: ='Staffing & Payroll'!E7 -> 24888.84 | E34: =OPEX!B11 -> 48200 | F34: =B34-C34-D34-E34 -> -9608.1731 | G34: =Financing!D34 -> 13152.112 | H34: =F33-G33 -> -24058.562
A35: 32 | B35: ='Revenue Model'!I36 -> 68638.892 | C35: =OPEX!E6 -> 3900 | D35: ='Staffing & Payroll'!E7 -> 24888.84 | E35: =OPEX!B11 -> 48200 | F35: =B35-C35-D35-E35 -> -8349.9476 | G35: =Financing!D35 -> 13051.353 | H35: =F34-G34 -> -22760.285
A36: 33 | B36: ='Revenue Model'!I37 -> 72209.199 | C36: =OPEX!E6 -> 3900 | D36: ='Staffing & Payroll'!E7 -> 24888.84 | E36: =OPEX!B11 -> 48200 | F36: =B36-C36-D36-E36 -> -4779.6408 | G36: =Financing!D36 -> 12949.797 | H36: =F35-G35 -> -21401.301
A37: 34 | B37: ='Revenue Model'!I38 -> 72713.687 | C37: =OPEX!E6 -> 3900 | D37: ='Staffing & Payroll'!E7 -> 24888.84 | E37: =OPEX!B11 -> 48200 | F37: =B37-C37-D37-E37 -> -4275.1526 | G37: =Financing!D37 -> 12847.437 | H37: =F36-G36 -> -17729.438
A38: 35 | B38: ='Revenue Model'!I39 -> 72962.909 | C38: =OPEX!E6 -> 3900 | D38: ='Staffing & Payroll'!E7 -> 24888.84 | E38: =OPEX!B11 -> 48200 | F38: =B38-C38-D38-E38 -> -4025.9313 | G38: =Financing!D38 -> 12744.266 | H38: =F37-G37 -> -17122.59
A39: 36 | B39: ='Revenue Model'!I40 -> 72648.365 | C39: =OPEX!E6 -> 3900 | D39: ='Staffing & Payroll'!E7 -> 24888.84 | E39: =OPEX!B11 -> 48200 | F39: =B39-C39-D39-E39 -> -4340.4755 | G39: =Financing!D39 -> 12640.279 | H39: =F38-G38 -> -16770.198
A40: 37 | B40: ='Revenue Model'!I41 -> 75074.377 | C40: =OPEX!E6 -> 3900 | D40: ='Staffing & Payroll'!E7 -> 24888.84 | E40: =OPEX!B11 -> 48200 | F40: =B40-C40-D40-E40 -> -1914.463 | G40: =Financing!D40 -> 12535.468 | H40: =F39-G39 -> -16980.754
A41: 38 | B41: ='Revenue Model'!I42 -> 82534.471 | C41: =OPEX!E6 -> 3900 | D41: ='Staffing & Payroll'!E7 -> 24888.84 | E41: =OPEX!B11 -> 48200 | F41: =B41-C41-D41-E41 -> 5545.6311 | G41: =Financing!D41 -> 12429.828 | H41: =F40-G40 -> -14449.931
A42: 39 | B42: ='Revenue Model'!I43 -> 84870.856 | C42: =OPEX!E6 -> 3900 | D42: ='Staffing & Payroll'!E7 -> 24888.84 | E42: =OPEX!B11 -> 48200 | F42: =B42-C42-D42-E42 -> 7882.0164 | G42: =Financing!D42 -> 12323.351 | H42: =F41-G41 -> -6884.197
A43: 40 | B43: ='Revenue Model'!I44 -> 86961.142 | C43: =OPEX!E6 -> 3900 | D43: ='Staffing & Payroll'!E7 -> 24888.84 | E43: =OPEX!B11 -> 48200 | F43: =B43-C43-D43-E43 -> 9972.3024 | G43: =Financing!D43 -> 12216.032 | H43: =F42-G42 -> -4441.335
A44: 41 | B44: ='Revenue Model'!I45 -> 89198.283 | C44: =OPEX!E6 -> 3900 | D44: ='Staffing & Payroll'!E7 -> 24888.84 | E44: =OPEX!B11 -> 48200 | F44: =B44-C44-D44-E44 -> 12209.443 | G44: =Financing!D44 -> 12107.863 | H44: =F43-G43 -> -2243.7294
A45: 42 | B45: ='Revenue Model'!I46 -> 90658.13 | C45: =OPEX!E6 -> 3900 | D45: ='Staffing & Payroll'!E7 -> 24888.84 | E45: =OPEX!B11 -> 48200 | F45: =B45-C45-D45-E45 -> 13669.29 | G45: =Financing!D45 -> 11998.837 | H45: =F44-G44 -> 101.58059
A46: 43 | B46: ='Revenue Model'!I47 -> 92190.97 | C46: =OPEX!E6 -> 3900 | D46: ='Staffing & Payroll'!E7 -> 24888.84 | E46: =OPEX!B11 -> 48200 | F46: =B46-C46-D46-E46 -> 15202.13 | G46: =Financing!D46 -> 11888.948 | H46: =F45-G45 -> 1670.4534
A47: 44 | B47: ='Revenue Model'!I48 -> 92771.149 | C47: =OPEX!E6 -> 3900 | D47: ='Staffing & Payroll'!E7 -> 24888.84 | E47: =OPEX!B11 -> 48200 | F47: =B47-C47-D47-E47 -> 15782.309 | G47: =Financing!D47 -> 11778.19 | H47: =F46-G46 -> 3313.1817
A48: 45 | B48: ='Revenue Model'!I49 -> 93328.871 | C48: =OPEX!E6 -> 3900 | D48: ='Staffing & Payroll'!E7 -> 24888.84 | E48: =OPEX!B11 -> 48200 | F48: =B48-C48-D48-E48 -> 16340.031 | G48: =Financing!D48 -> 11666.554 | H48: =F47-G47 -> 4004.119
A49: 46 | B49: ='Revenue Model'!I50 -> 93893.771 | C49: =OPEX!E6 -> 3900 | D49: ='Staffing & Payroll'!E7 -> 24888.84 | E49: =OPEX!B11 -> 48200 | F49: =B49-C49-D49-E49 -> 16904.931 | G49: =Financing!D49 -> 11554.035 | H49: =F48-G48 -> 4673.4769
A50: 47 | B50: ='Revenue Model'!I51 -> 95207.603 | C50: =OPEX!E6 -> 3900 | D50: ='Staffing & Payroll'!E7 -> 24888.84 | E50: =OPEX!B11 -> 48200 | F50: =B50-C50-D50-E50 -> 18218.763 | G50: =Financing!D50 -> 11440.625 | H50: =F49-G49 -> 5350.8955
A51: 48 | B51: ='Revenue Model'!I52 -> 97266.394 | C51: =OPEX!E6 -> 3900 | D51: ='Staffing & Payroll'!E7 -> 24888.84 | E51: =OPEX!B11 -> 48200 | F51: =B51-C51-D51-E51 -> 20277.554 | G51: =Financing!D51 -> 11326.317 | H51: =F50-G50 -> 6778.1383

Sheet Cash Flow
A1: Cash Flow – Monthly (36 months)
A2: Predicted Cash Flow
A3: Month | B3: EBITDA | C3: Interest | D3: Debt Service (PMT) | E3: Principal | F3: CapEx | G3: Net Cash Flow | H3: Cash Balance
A4: 1 | B4: ='P&L (36m)'!F4 -> -16910.002 | C4: ='P&L (36m)'!G4 -> 15833.333 | D4: =MonthlyDebtService -> 25879.512 | E4: =D4-C4 -> 10046.178 | F4: ='CapEx & Sources'!E22 -> 799260 | G4: =B4-C4-F4 -> -832003.34 | H4: =Assumptions!$B$41 + Financing!$B$4 + ABS('CapEx & Sources'!$H$5) -F4 +G4 -> 1569476.7
A5: 2 | B5: ='P&L (36m)'!F4 -> -16910.002 | C5: ='P&L (36m)'!G4 -> 15833.333 | D5: =MonthlyDebtService -> 25879.512 | E5: =D5-C5 -> 10046.178 | F5: 0 | G5: =B5-C5-F5 -> -32743.335 | H5: =H4+G5 -> 1536733.3
A6: 3 | B6: ='P&L (36m)'!F5 -> -15705.189 | C6: ='P&L (36m)'!G5 -> 15753.801 | D6: =MonthlyDebtService -> 25879.512 | E6: =D6-C6 -> 10125.71 | F6: 0 | G6: =B6-C6-F6 -> -31458.991 | H6: =H5+G6 -> 1505274.3
A7: 4 | B7: ='P&L (36m)'!F6 -> -20302.444 | C7: ='P&L (36m)'!G6 -> 15673.639 | D7: =MonthlyDebtService -> 25879.512 | E7: =D7-C7 -> 10205.872 | F7: 0 | G7: =B7-C7-F7 -> -35976.083 | H7: =H6+G7 -> 1469298.3
A8: 5 | B8: ='P&L (36m)'!F7 -> -20489.622 | C8: ='P&L (36m)'!G7 -> 15592.843 | D8: =MonthlyDebtService -> 25879.512 | E8: =D8-C8 -> 10286.669 | F8: 0 | G8: =B8-C8-F8 -> -36082.464 | H8: =H7+G8 -> 1433215.8
A9: 6 | B9: ='P&L (36m)'!F8 -> -23907.072 | C9: ='P&L (36m)'!G8 -> 15511.407 | D9: =MonthlyDebtService -> 25879.512 | E9: =D9-C9 -> 10368.105 | F9: 0 | G9: =B9-C9-F9 -> -39418.479 | H9: =H8+G9 -> 1393797.3
A10: 7 | B10: ='P&L (36m)'!F9 -> -27341.533 | C10: ='P&L (36m)'!G9 -> 15429.326 | D10: =MonthlyDebtService -> 25879.512 | E10: =D10-C10 -> 10450.186 | F10: 0 | G10: =B10-C10-F10 -> -42770.859 | H10: =H9+G10 -> 1351026.5
A11: 8 | B11: ='P&L (36m)'!F10 -> -26969.976 | C11: ='P&L (36m)'!G10 -> 15346.595 | D11: =MonthlyDebtService -> 25879.512 | E11: =D11-C11 -> 10532.916 | F11: 0 | G11: =B11-C11-F11 -> -42316.571 | H11: =H10+G11 -> 1308709.9
A12: 9 | B12: ='P&L (36m)'!F11 -> -26579.84 | C12: ='P&L (36m)'!G11 -> 15263.21 | D12: =MonthlyDebtService -> 25879.512 | E12: =D12-C12 -> 10616.302 | F12: 0 | G12: =B12-C12-F12 -> -41843.05 | H12: =H11+G12 -> 1266866.8
A13: 10 | B13: ='P&L (36m)'!F12 -> -22305.253 | C13: ='P&L (36m)'!G12 -> 15179.164 | D13: =MonthlyDebtService -> 25879.512 | E13: =D13-C13 -> 10700.348 | F13: 0 | G13: =B13-C13-F13 -> -37484.417 | H13: =H12+G13 -> 1229382.4
A14: 11 | B14: ='P&L (36m)'!F13 -> -18315.594 | C14: ='P&L (36m)'!G13 -> 15094.453 | D14: =MonthlyDebtService -> 25879.512 | E14: =D14-C14 -> 10785.059 | F14: 0 | G14: =B14-C14-F14 -> -33410.047 | H14: =H13+G14 -> 1195972.4
A15: 12 | B15: ='P&L (36m)'!F14 -> -18238.319 | C15: ='P&L (36m)'!G14 -> 15009.071 | D15: =MonthlyDebtService -> 25879.512 | E15: =D15-C15 -> 10870.44 | F15: 0 | G15: =B15-C15-F15 -> -33247.39 | H15: =H14+G15 -> 1162725
A16: 13 | B16: ='P&L (36m)'!F15 -> -18335.849 | C16: ='P&L (36m)'!G15 -> 14923.013 | D16: =MonthlyDebtService -> 25879.512 | E16: =D16-C16 -> 10956.498 | F16: 0 | G16: =B16-C16-F16 -> -33258.862 | H16: =H15+G16 -> 1129466.1
... A39: 36 | B39: ='P&L (36m)'!F38 -> -4025.9313 | C39: ='P&L (36m)'!G38 -> 12744.266 | D39: =MonthlyDebtService -> 25879.512 | E39: =D39-C39 -> 13135.245 | F39: 0 | G39: =B39-C39-F39 -> -16770.198 | H39: =H38+G39 -> 513831.02
A40: 37 | B40: ='P&L (36m)'!F40 -> -1914.463 | C40: ='P&L (36m)'!G40 -> 12535.468 | D40: =MonthlyDebtService -> 25879.512 | E40: =D40-C40 -> 13344.043 | F40: ='CapEx & Sources'!E58 -> 0 | G40: =B40-C40-F40 -> -14449.931 | H40: =H39+G40 -> 499381.09
A41: 38 | B41: ='P&L (36m)'!F40 -> -1914.463 | C41: ='P&L (36m)'!G40 -> 12535.468 | D41: =MonthlyDebtService -> 25879.512 | E41: =D41-C41 -> 13344.043 | F41: 0 | G41: =B41-C41-F41 -> -14449.931 | H41: =H40+G41 -> 484931.16
A42: 39 | B42: ='P&L (36m)'!F41 -> 5545.6311 | C42: ='P&L (36m)'!G41 -> 12429.828 | D42: =MonthlyDebtService -> 25879.512 | E42: =D42-C42 -> 13449.683 | F42: 0 | G42: =B42-C42-F42 -> -6884.197 | H42: =H41+G42 -> 478046.96
A43: 40 | B43: ='P&L (36m)'!F42 -> 7882.0164 | C43: ='P&L (36m)'!G42 -> 12323.351 | D43: =MonthlyDebtService -> 25879.512 | E43: =D43-C43 -> 13556.16 | F43: 0 | G43: =B43-C43-F43 -> -4441.335 | H43: =H42+G43 -> 473605.63
A44: 41 | B44: ='P&L (36m)'!F43 -> 9972.3024 | C44: ='P&L (36m)'!G43 -> 12216.032 | D44: =MonthlyDebtService -> 25879.512 | E44: =D44-C44 -> 13663.48 | F44: 0 | G44: =B44-C44-F44 -> -2243.7294 | H44: =H43+G44 -> 471361.9
A45: 42 | B45: ='P&L (36m)'!F44 -> 12209.443 | C45: ='P&L (36m)'!G44 -> 12107.863 | D45: =MonthlyDebtService -> 25879.512 | E45: =D45-C45 -> 13771.649 | F45: 0 | G45: =B45-C45-F45 -> 101.58059 | H45: =H44+G45 -> 471463.48
A46: 43 | B46: ='P&L (36m)'!F45 -> 13669.29 | C46: ='P&L (36m)'!G45 -> 11998.837 | D46: =MonthlyDebtService -> 25879.512 | E46: =D46-C46 -> 13880.674 | F46: 0 | G46: =B46-C46-F46 -> 1670.4534 | H46: =H45+G46 -> 473133.93
A47: 44 | B47: ='P&L (36m)'!F46 -> 15202.13 | C47: ='P&L (36m)'!G46 -> 11888.948 | D47: =MonthlyDebtService -> 25879.512 | E47: =D47-C47 -> 13990.563 | F47: 0 | G47: =B47-C47-F47 -> 3313.1817 | H47: =H46+G47 -> 476447.11
A48: 45 | B48: ='P&L (36m)'!F47 -> 15782.309 | C48: ='P&L (36m)'!G47 -> 11778.19 | D48: =MonthlyDebtService -> 25879.512 | E48: =D48-C48 -> 14101.322 | F48: 0 | G48: =B48-C48-F48 -> 4004.119 | H48: =H47+G48 -> 480451.23
A49: 46 | B49: ='P&L (36m)'!F48 -> 16340.031 | C49: ='P&L (36m)'!G48 -> 11666.554 | D49: =MonthlyDebtService -> 25879.512 | E49: =D49-C49 -> 14212.957 | F49: 0 | G49: =B49-C49-F49 -> 4673.4769 | H49: =H48+G49 -> 485124.71
A50: 47 | B50: ='P&L (36m)'!F49 -> 16904.931 | C50: ='P&L (36m)'!G49 -> 11554.035 | D50: =MonthlyDebtService -> 25879.512 | E50: =D50-C50 -> 14325.476 | F50: 0 | G50: =B50-C50-F50 -> 5350.8955 | H50: =H49+G50 -> 490475.6
A51: 48 | B51: ='P&L (36m)'!F50 -> 18218.763 | C51: ='P&L (36m)'!G50 -> 11440.625 | D51: =MonthlyDebtService -> 25879.512 | E51: =D51-C51 -> 14438.886 | F51: 0 | G51: =B51-C51-F51 -> 6778.1383 | H51: =H50+G51 -> 497253.74

Sheet KPIs
A1: Key Performance Indicators
A3: Metric | B3: Value | C3: Definition | D3: Formula
A4: Average Monthly Utilization (model input) | B4: =(Assumptions!B10*Assumptions!B11 + (1-Assumptions!B10)*Assumptions!B12) -> 0.535 | C4: Weighted usage rate | D4: PeakHoursShare*UtilPeak + (1-PeakHoursShare)*UtilOffPeak
A5: Revenue / Court / Hour (approx) | B5: ='Revenue Model'!B5 / (Assumptions!B7*Assumptions!B8*4.33*Assumptions!B9*(Assumptions!B10*Assumptions!B11 + (1-Assumptions!B10)*Assumptions!B12)) -> 21.843453 | C5: Efficiency measurement | D5: CourtRevenue / (Courts * Hours * Util * Days * Weeks)
A6: Payroll % of Revenue (Month 1) | B6: ='Staffing & Payroll'!E7 / 'Revenue Model'!I5 -> 0.41426966 | C6: Initial Cost ratio of Payroll | D6: MonthlyPayroll / TotalRevenue
A7: EBITDA Margin (Month 1) | B7: ='P&L (36m)'!F4/'P&L (36m)'!B4 -> -0.28146353 | C7: Initial Profitability margin | D7: EBITDA / Revenue
A8: Cash Runway (months) | B8: =IFERROR( 'Cash Flow'!H4 / ABS(AVERAGE('Cash Flow'!G5:G51)), 999) -> 68.796704 | C8: 0

Sheet Maintenance & Safety
A1: Preventive Maintenance Schedule
A3: Area/Asset | B3: Task | C3: Frequency | D3: Next Due | E3: Assigned To | F3: Status | G3: Notes
A4: Courts (surface/lines) | B4: Inspect/clean; check wear | C4: Monthly | F4: Open
A5: Lighting | B5: Test lux levels; replace failures | C5: Quarterly | F5: Open
A6: HVAC | B6: Filter change; service | C6: Quarterly | F6: Open
A7: Nets/Posts | B7: Tension & wear check | C7: Monthly | F7: Open
A8: Safety | B8: First-aid kits; AED check | C8: Monthly | F8: Open
A10: Incident Log
A11: Date | B11: Description | C11: Injury? (Y/N) | D11: Employee Involved | E11: Action Taken | F11: Follow-up Due

Sheet Events & Leagues
A1: Leagues & Events Tracker
A2: Use generators to export round-robin/brackets and paste key totals here.
A3: Event/League | B3: Start | C3: End | D3: Teams/Players | E3: Entry Fee | F3: Revenue | G3: Staff Hours | H3: Notes

Sheet README + Links
A1: How to Use This Workbook
A3: 1) Start at the Assumptions tab. Update blue cells (pricing, utilization, wages, rent, loan).
A4: 2) Fill CapEx & Sources. Adjust line items and contingency.
A5: 3) Revenue, P&L, Cash Flow, and KPIs will auto-update.
A7: Helpful External Templates (paste exports into tabs):
A8: Vertex42 Loan Amortization (Excel)
A9: LeagueLobster Round-Robin Generator
A10: Bracket Maker – Round Robin
A11: Marketing Budget Templates
A13: Notes:
A14: • Replace placeholder CapEx with vendor quotes. • If you prefer Google Sheets, upload this .xlsx—formulas will port cleanly. • Extend P&L/Cash Flow from 36 → 60 months by filling down.

Sheet Court Revenue OLD
A1: Court Revenue – Advanced Model (Peak/Off-Peak • Open Play • Members vs Non-Members)
A2: Paste into your master workbook. Link to Memberships tab for live members if desired.
A4: INPUTS – Facility & Scheduling | E4: INPUTS – Pricing
A5: Courts (count) | B5: 8 | E5: Peak rate – Non-member ($/court-hr) | F5: 70
A6: Days open per week | B6: 7 | E6: Off-peak rate – Non-member ($/court-hr) | F6: 50
A7: Hours open per day | B7: 14 | E7: Member discount on court rate | F7: 0.25
A8: Peak hours share of day | B8: 0.5 | E8: Open Play price – Member ($/session) | F8: 8
A9: Weekend share of days | B9: 0.28571429 | E9: Open Play price – Non-member ($/session) | F9: 12
A10: Avg reservation duration (min) | B10: 90 | E10: Open Play session length (min) | F10: 120
A11: Turn time between bookings (min) | B11: 5 | E11: Open Play players per court capacity (per hour) | F11: 6
E12: INPUTS – Membership Link (optional)
A13: INPUTS – Demand & Behavior | B13: Conservative Estimate | E13: Total Members: | F13: =Assumptions!B16 -> 50 | J13: Liberal Estimate
A14: Baseline utilization – Peak (weekday) | B14: 0.5 | E14: % Members who reserve monthly: | F14: 0.6 | J14: 0.75
A15: Baseline utilization – Off-peak (weekday) | B15: 0.3 | E15: Avg reservations per reserving member / month: | F15: 2 | J15: 0.4
A16: Baseline utilization – Peak (weekend) | B16: 0.7 | E16: Avg open play sessions per member / month: | F16: 1.2 | J16: 0.85
A17: Baseline utilization – Off-peak (weekend) | B17: 0.4 | J17: 0.5
A18: Member booking share of reservations | B18: 0.7 | J18: 0.7
A19: Booking window uplift (members vs non) | B19: 0.05 | J19: 0.05
A20: No-show rate (paid/no-refund portion) | B20: 0.05 | J20: 0.05
A21: Reservation share of total court time (vs open play) | B21: 0.5 | J21: 0.7
A23: HELPERS
A24: Court-hours available per month | B24: =B5*B6*4.33*B7 -> 3394.72
A25: Peak hours per month | B25: =B24*B8 -> 1697.36
A26: Off-peak hours per month | B26: =B24*(1-B8) -> 1697.36
A27: Bookings per court-day capacity (duration + turn) | B27: =FLOOR((B7*60)/(B10+B11),1) -> 8
A28: Reservation hours share | B28: =B21 -> 0.5
A29: Open Play hours share | B29: =(1-B21) -> 0.5
A30: Blended peak utilization (wkdy/wknd) | B30: =(1-B9)*B14+ B8*B16 -> 0.70714286
A31: Blended off-peak utilization (wkdy/wknd) | B31: =(1-B9)*B15 + B9*B17 -> 0.32857143
A33: RESERVATIONS – Revenue
A34: Segment | B34: Peak hours sold | C34: Off-peak hours sold | D34: Total hours (attended) | E34: Avg rate ($/hr) | F34: Revenue ($, attended)
A35: Members | B35: =B25*$B$30*$B$21*B18*(1+B19) -> 441.10143 | C35: =B26*$B$31*$B$21*$B$18*(1+$B$19) -> 204.95622 | D35: =B35+C35 -> 646.05765 | E35: =IFERROR(((F5*(1-F7))*B35 + (F6*(1-F7))*C35)/D35,0) -> 47.741379 | F35: =D35*E35 -> 30843.683
A36: Non-members | B36: =B25*$B$30*$B$21*(1-$B$18) -> 180.0414 | C36: =B26*$B$31*$B$21*(1-$B$18) -> 83.6556 | D36: =B36+C36 -> 263.697 | E36: =IFERROR((F5*B36 + F6*C36)/D36,0) -> 63.655172 | F36: =D36*E36 -> 16785.678
A37: Reservations TOTAL | B37: =B35+B36 -> 621.14283 | C37: =C35+C36 -> 288.61182 | D37: =D35+D36 -> 909.75465 | E37: =IFERROR((E35*D35+E36*D36)/D37,0) -> 52.354073 | F37: =F35+F36 -> 47629.361
A39: No-show charged revenue (policy-based, not in hours) | B39: =$E$37*$B$37*$B$20 -> 1625.9679
A41: OPEN PLAY – Revenue
A42: Segment | B42: Court-hours allocated | C42: Sessions (blocks) | D42: Players per hour | E42: Avg price/session | F42: Revenue ($)
A43: Members | B43: =(B29*B24)*$B$18 -> 1188.152 | C43: =IFERROR(B43/(F10/60),0) -> 594.076 | D43: =F11 -> 6 | E43: =F8 -> 8 | F43: =C43*E43 -> 4752.608
A44: Non-members | B44: =B29*B24*(1-$B$18) -> 509.208 | C44: =IFERROR(B44/(F10/60),0) -> 254.604 | D44: =F11 -> 6 | E44: =F9 -> 12 | F44: =C44*E44 -> 3055.248
A45: Open Play TOTAL | B45: =B43+B44 -> 1697.36 | C45: =C43+C44 -> 848.68 | F45: =F43+F44 -> 7807.856
A47: TOTALS & KPIs
A48: Metric | B48: Value
A49: Court Revenue – Reservations (incl. no-shows) ($/mo) | B49: =$F$37+$B$39 -> 49255.329
A50: Court Revenue – Open Play ($/mo) | B50: =$F$45 -> 7807.856
A51: Court Revenue – TOTAL ($/mo) | B51: =$B$49+$B$50 -> 57063.185
A52: No-show charged revenue ($/mo) | B52: =$B$39 -> 1625.9679
A53: Court-hours sold – Reservations (attended) | B53: =$D$37 -> 909.75465
A54: Court-hours sold – Open Play | B54: =$B$45 -> 1697.36
A55: Utilization (attended hours / available) | B55: =(D37+B45)/B24 -> 0.76799107
A56: Yield ($ per attended sold court-hour) | B56: =(F37+F45)/(D37+B45) -> 21.26382
A57: Mix: % Member revenue (reservations, attended) | B57: =IFERROR(F35/F37,0) -> 0.64757709
A58: Mix: % Member revenue (open play) | B58: =IFERROR(F43/F45,0) -> 0.60869565
A60: Wire-up instructions
A61: • Link 'Revenue Model' → Court Revenue to cell B51 (TOTAL).
A62: • Link Total Members (F14) to Memberships! cell for live updates (optional).
A63: • Tweak utilizations (B14:B17), reservation share (B21), & booking uplift (B19) to match observed demand.
